Workbook

Sheet Portada
A1: PRUEBAS MANUALES - ESTÉTICA Y BELLEZA STRANI
A3: Proyecto: | B3: Estética y Belleza Strani
A4: Fecha: | B4: 2026-09-03
A5: Versión: | B5: 1.0
A6: Entorno: | B6: Flutter Web (producción) + Supabase (hhyjremkguvphmjuaazp)
A8: Instrucciones:
A9: 1. Cada hoja representa un módulo o flujo de la aplicación
A10: 2. Ejecute los pasos en orden y registre el Resultado (Pasa/Falla/Bloqueado/Pendiente)
A11: 3. Para fallas, documente en la columna Notas el comportamiento observado
A12: 4. Use la hoja Resumen_ejecucion para ver el estado global
A13: 5. Prioridades: Crítica (bloquea release), Alta (importante), Media (estándar), Baja (cosmético)
A14: 6. Tipos: Real (escenario con cuentas reales), Simulado (edge case, error, boundary)
A16: Estructura del libro:
A17: - Hojas 1-4: Portada, Guía, Matriz de cuentas, Resumen
A18: - Hojas 5-17: Casos existentes (01_auth_users a 13_admin_dashboard)
A19: - Hojas 18-23: Casos nuevos (14_notificaciones a 19_sesion_web)

Sheet Como_evaluar
A1: GUÍA DE EVALUACIÓN
A3: Criterios de resultado:
A4: Pasa | B4: El comportamiento observado coincide con el resultado esperado
A5: Falla | B5: El comportamiento observado difiere del resultado esperado (bug)
A6: Bloqueado | B6: No se puede ejecutar por dependencia de otro caso o problema de entorno
A7: Pendiente | B7: Aún no se ha ejecutado
A9: Prioridades:
A10: Crítica | B10: Bloquea el release. Debe corregirse antes de desplegar
A11: Alta | B11: Importante para la funcionalidad principal. Debe corregirse pronto
A12: Media | B12: Estándar. Se corrige en el ciclo normal
A13: Baja | B13: Cosmético o menor. Se corrige cuando haya tiempo
A15: Tipos de escenario:
A16: Real | B16: Escenario con cuentas de prueba reales, Stripe test mode, emails reales
A17: Simulado | B17: Edge case, error, boundary, concurrencia forzada, datos inválidos
A19: Plantilla para reportar bugs:
A20: ID del caso: | B20: [ID del caso que falló]
A21: Módulo: | B21: [Nombre del módulo]
A22: Pasos para reproducir: | B22: [Lista numerada de pasos]
A23: Resultado esperado: | B23: [Qué debería pasar]
A24: Resultado observado: | B24: [Qué pasó realmente]
A25: Entorno: | B25: [Browser, versión, OS]
A26: Evidencia: | B26: [Screenshot, video, logs]
A27: Prioridad sugerida: | B27: [Crítica/Alta/Media/Baja]

Sheet Matriz_cuentas
A1: MATRIZ DE CUENTAS DE PRUEBA
A3: Rol | B3: Email | C3: Password | D3: Estado | E3: Notas | F3: Uso en pruebas
A4: Paciente | B4: pac.activo@test | C4: Test1234! | D4: Activo (perfil completo) | E4: Email confirmado, dirección con geo | F4: Flujos completos de paciente
A5: Paciente | B5: pac.nuevo@test | C5: Test1234! | D5: Inactivo (sin perfil) | E5: Recién registrado | F5: Onboarding, activación
A6: Paciente | B6: pac.vencido@test | C6: Test1234! | D6: VENCIDA | E6: Evaluación vencida | F6: Re-evaluación
A7: Paciente | B7: pac.rechazado@test | C7: Test1234! | D7: Rechazado | E7: Evaluación rechazada | F7: Feedback re-evaluación
A8: Paciente | B8: pac.desactivado@test | C8: Test1234! | D8: Desactivado | E8: activo=false | F8: Guards, logout forzado
A9: Especialista | B9: esp.aprobado@test | C9: Test1234! | D9: APROBADO | E9: Sin geo (pruebas geofencing) | F9: Verificación, marketplace
A10: Especialista | B10: esp.nuevo@test | C10: Test1234! | D10: Sin verificación | E10: Recién registrado | F10: Flujo de verificación
A11: Especialista | B11: esp.revision@test | C11: Test1234! | D11: EN_REVISION | E11: Documentos enviados | F11: Revisión admin
A12: Especialista | B12: esp.rechazado@test | C12: Test1234! | D12: RECHAZADO | E12: Documentos rechazados | F12: Feedback, reenvío
A13: Especialista | B13: esp.bloqueado@test | C13: Test1234! | D13: BLOQUEADO | E13: Bloqueado por admin | F13: Guard, logout
A14: Especialista | B14: esp.desactivado@test | C14: Test1234! | D14: Desactivado | E14: activo=false | F14: Guards, logout forzado
A15: Administrador | B15: admin@test | C15: Test1234! | D15: Activo | E15: Acceso total | F15: Todas las vistas admin
A17: Entorno de pruebas:
A18: URL: | B18: https://esteticaybellezastrani.web.app
A19: Supabase: | B19: hhyjremkguvphmjuaazp (producción)
A20: Stripe: | B20: Test mode (tarjetas de prueba)
A21: Email: | B21: Real (Supabase Auth)

Sheet Resumen_ejecucion
A1: RESUMEN EJECUTIVO - CUADRO DE CONTROL
A3: 1. CONTEO POR MÓDULO
A4: Módulo | B4: Total | C4: Pasa | D4: Falla | E4: Bloqueado | F4: Pendiente | G4: % Pase | H4: Fallas Críticas
A5: 01_auth_users | B5: =COUNTA('01_auth_users'!A2:A1000) -> 49 | C5: =COUNTIF('01_auth_users'!I2:I1000,"Pasa") -> 36 | D5: =COUNTIF('01_auth_users'!I2:I1000,"Falla") -> 3 | E5: =COUNTIF('01_auth_users'!I2:I1000,"Bloqueado") -> 0 | F5: =COUNTIF('01_auth_users'!I2:I1000,"Pendiente")+COUNTBLANK('01_auth_users'!I2:I1000)-COUNTBLANK('01_auth_users'!A2:A1000) -> 10 | G5: =IF(B5=0,0,C5/B5) -> 0.73469388 | H5: =COUNTIFS('01_auth_users'!G2:G1000,"Crítica",'01_auth_users'!I2:I1000,"Falla") -> 0
A6: 02_specialists | B6: =COUNTA('02_specialists'!A2:A1000) -> 44 | C6: =COUNTIF('02_specialists'!I2:I1000,"Pasa") -> 17 | D6: =COUNTIF('02_specialists'!I2:I1000,"Falla") -> 1 | E6: =COUNTIF('02_specialists'!I2:I1000,"Bloqueado") -> 1 | F6: =COUNTIF('02_specialists'!I2:I1000,"Pendiente")+COUNTBLANK('02_specialists'!I2:I1000)-COUNTBLANK('02_specialists'!A2:A1000) -> 25 | G6: =IF(B6=0,0,C6/B6) -> 0.38636364 | H6: =COUNTIFS('02_specialists'!G2:G1000,"Crítica",'02_specialists'!I2:I1000,"Falla") -> 0
A7: 03_admin_config | B7: =COUNTA('03_admin_config'!A2:A1000) -> 29 | C7: =COUNTIF('03_admin_config'!I2:I1000,"Pasa") -> 0 | D7: =COUNTIF('03_admin_config'!I2:I1000,"Falla") -> 0 | E7: =COUNTIF('03_admin_config'!I2:I1000,"Bloqueado") -> 0 | F7: =COUNTIF('03_admin_config'!I2:I1000,"Pendiente")+COUNTBLANK('03_admin_config'!I2:I1000)-COUNTBLANK('03_admin_config'!A2:A1000) -> 29 | G7: =IF(B7=0,0,C7/B7) -> 0 | H7: =COUNTIFS('03_admin_config'!G2:G1000,"Crítica",'03_admin_config'!I2:I1000,"Falla") -> 0
A8: 04_admin_users | B8: =COUNTA('04_admin_users'!A2:A1000) -> 19 | C8: =COUNTIF('04_admin_users'!I2:I1000,"Pasa") -> 0 | D8: =COUNTIF('04_admin_users'!I2:I1000,"Falla") -> 0 | E8: =COUNTIF('04_admin_users'!I2:I1000,"Bloqueado") -> 0 | F8: =COUNTIF('04_admin_users'!I2:I1000,"Pendiente")+COUNTBLANK('04_admin_users'!I2:I1000)-COUNTBLANK('04_admin_users'!A2:A1000) -> 19 | G8: =IF(B8=0,0,C8/B8) -> 0 | H8: =COUNTIFS('04_admin_users'!G2:G1000,"Crítica",'04_admin_users'!I2:I1000,"Falla") -> 0
A9: 05_catalog_services | B9: =COUNTA('05_catalog_services'!A2:A1000) -> 27 | C9: =COUNTIF('05_catalog_services'!I2:I1000,"Pasa") -> 0 | D9: =COUNTIF('05_catalog_services'!I2:I1000,"Falla") -> 0 | E9: =COUNTIF('05_catalog_services'!I2:I1000,"Bloqueado") -> 0 | F9: =COUNTIF('05_catalog_services'!I2:I1000,"Pendiente")+COUNTBLANK('05_catalog_services'!I2:I1000)-COUNTBLANK('05_catalog_services'!A2:A1000) -> 27 | G9: =IF(B9=0,0,C9/B9) -> 0 | H9: =COUNTIFS('05_catalog_services'!G2:G1000,"Crítica",'05_catalog_services'!I2:I1000,"Falla") -> 0
A10: 06_marketplace_citas | B10: =COUNTA('06_marketplace_citas'!A2:A1000) -> 31 | C10: =COUNTIF('06_marketplace_citas'!I2:I1000,"Pasa") -> 0 | D10: =COUNTIF('06_marketplace_citas'!I2:I1000,"Falla") -> 0 | E10: =COUNTIF('06_marketplace_citas'!I2:I1000,"Bloqueado") -> 0 | F10: =COUNTIF('06_marketplace_citas'!I2:I1000,"Pendiente")+COUNTBLANK('06_marketplace_citas'!I2:I1000)-COUNTBLANK('06_marketplace_citas'!A2:A1000) -> 21 | G10: =IF(B10=0,0,C10/B10) -> 0 | H10: =COUNTIFS('06_marketplace_citas'!G2:G1000,"Crítica",'06_marketplace_citas'!I2:I1000,"Falla") -> 0
A11: 07_patients_compliance | B11: =COUNTA('07_patients_compliance'!A2:A1000) -> 31 | C11: =COUNTIF('07_patients_compliance'!I2:I1000,"Pasa") -> 0 | D11: =COUNTIF('07_patients_compliance'!I2:I1000,"Falla") -> 0 | E11: =COUNTIF('07_patients_compliance'!I2:I1000,"Bloqueado") -> 0 | F11: =COUNTIF('07_patients_compliance'!I2:I1000,"Pendiente")+COUNTBLANK('07_patients_compliance'!I2:I1000)-COUNTBLANK('07_patients_compliance'!A2:A1000) -> 31 | G11: =IF(B11=0,0,C11/B11) -> 0 | H11: =COUNTIFS('07_patients_compliance'!G2:G1000,"Crítica",'07_patients_compliance'!I2:I1000,"Falla") -> 0
A12: 08_payments_stripe | B12: =COUNTA('08_payments_stripe'!A2:A1000) -> 23 | C12: =COUNTIF('08_payments_stripe'!I2:I1000,"Pasa") -> 0 | D12: =COUNTIF('08_payments_stripe'!I2:I1000,"Falla") -> 0 | E12: =COUNTIF('08_payments_stripe'!I2:I1000,"Bloqueado") -> 0 | F12: =COUNTIF('08_payments_stripe'!I2:I1000,"Pendiente")+COUNTBLANK('08_payments_stripe'!I2:I1000)-COUNTBLANK('08_payments_stripe'!A2:A1000) -> 23 | G12: =IF(B12=0,0,C12/B12) -> 0 | H12: =COUNTIFS('08_payments_stripe'!G2:G1000,"Crítica",'08_payments_stripe'!I2:I1000,"Falla") -> 0
A13: 09_treatment_execution | B13: =COUNTA('09_treatment_execution'!A2:A1000) -> 33 | C13: =COUNTIF('09_treatment_execution'!I2:I1000,"Pasa") -> 0 | D13: =COUNTIF('09_treatment_execution'!I2:I1000,"Falla") -> 0 | E13: =COUNTIF('09_treatment_execution'!I2:I1000,"Bloqueado") -> 0 | F13: =COUNTIF('09_treatment_execution'!I2:I1000,"Pendiente")+COUNTBLANK('09_treatment_execution'!I2:I1000)-COUNTBLANK('09_treatment_execution'!A2:A1000) -> 33 | G13: =IF(B13=0,0,C13/B13) -> 0 | H13: =COUNTIFS('09_treatment_execution'!G2:G1000,"Crítica",'09_treatment_execution'!I2:I1000,"Falla") -> 0
A14: 10_treatment_photos | B14: =COUNTA('10_treatment_photos'!A2:A1000) -> 20 | C14: =COUNTIF('10_treatment_photos'!I2:I1000,"Pasa") -> 0 | D14: =COUNTIF('10_treatment_photos'!I2:I1000,"Falla") -> 0 | E14: =COUNTIF('10_treatment_photos'!I2:I1000,"Bloqueado") -> 0 | F14: =COUNTIF('10_treatment_photos'!I2:I1000,"Pendiente")+COUNTBLANK('10_treatment_photos'!I2:I1000)-COUNTBLANK('10_treatment_photos'!A2:A1000) -> 20 | G14: =IF(B14=0,0,C14/B14) -> 0 | H14: =COUNTIFS('10_treatment_photos'!G2:G1000,"Crítica",'10_treatment_photos'!I2:I1000,"Falla") -> 0
A15: 12_solicitudes_reserva | B15: =COUNTA('12_solicitudes_reserva'!A2:A1000) -> 14 | C15: =COUNTIF('12_solicitudes_reserva'!I2:I1000,"Pasa") -> 0 | D15: =COUNTIF('12_solicitudes_reserva'!I2:I1000,"Falla") -> 0 | E15: =COUNTIF('12_solicitudes_reserva'!I2:I1000,"Bloqueado") -> 0 | F15: =COUNTIF('12_solicitudes_reserva'!I2:I1000,"Pendiente")+COUNTBLANK('12_solicitudes_reserva'!I2:I1000)-COUNTBLANK('12_solicitudes_reserva'!A2:A1000) -> 0 | G15: =IF(B15=0,0,C15/B15) -> 0 | H15: =COUNTIFS('12_solicitudes_reserva'!G2:G1000,"Crítica",'12_solicitudes_reserva'!I2:I1000,"Falla") -> 0
A16: 13_admin_dashboard | B16: =COUNTA('13_admin_dashboard'!A2:A1000) -> 11 | C16: =COUNTIF('13_admin_dashboard'!I2:I1000,"Pasa") -> 0 | D16: =COUNTIF('13_admin_dashboard'!I2:I1000,"Falla") -> 0 | E16: =COUNTIF('13_admin_dashboard'!I2:I1000,"Bloqueado") -> 0 | F16: =COUNTIF('13_admin_dashboard'!I2:I1000,"Pendiente")+COUNTBLANK('13_admin_dashboard'!I2:I1000)-COUNTBLANK('13_admin_dashboard'!A2:A1000) -> 11 | G16: =IF(B16=0,0,C16/B16) -> 0 | H16: =COUNTIFS('13_admin_dashboard'!G2:G1000,"Crítica",'13_admin_dashboard'!I2:I1000,"Falla") -> 0
A17: 14_Notificaciones | B17: =COUNTA('14_Notificaciones'!A2:A1000) -> 15 | C17: =COUNTIF('14_Notificaciones'!I2:I1000,"Pasa") -> 0 | D17: =COUNTIF('14_Notificaciones'!I2:I1000,"Falla") -> 0 | E17: =COUNTIF('14_Notificaciones'!I2:I1000,"Bloqueado") -> 0 | F17: =COUNTIF('14_Notificaciones'!I2:I1000,"Pendiente")+COUNTBLANK('14_Notificaciones'!I2:I1000)-COUNTBLANK('14_Notificaciones'!A2:A1000) -> 15 | G17: =IF(B17=0,0,C17/B17) -> 0 | H17: =COUNTIFS('14_Notificaciones'!G2:G1000,"Crítica",'14_Notificaciones'!I2:I1000,"Falla") -> 0
A18: 15_Calificaciones | B18: =COUNTA('15_Calificaciones'!A2:A1000) -> 13 | C18: =COUNTIF('15_Calificaciones'!I2:I1000,"Pasa") -> 0 | D18: =COUNTIF('15_Calificaciones'!I2:I1000,"Falla") -> 0 | E18: =COUNTIF('15_Calificaciones'!I2:I1000,"Bloqueado") -> 0 | F18: =COUNTIF('15_Calificaciones'!I2:I1000,"Pendiente")+COUNTBLANK('15_Calificaciones'!I2:I1000)-COUNTBLANK('15_Calificaciones'!A2:A1000) -> 13 | G18: =IF(B18=0,0,C18/B18) -> 0 | H18: =COUNTIFS('15_Calificaciones'!G2:G1000,"Crítica",'15_Calificaciones'!I2:I1000,"Falla") -> 0
A19: 16_Liquidaciones | B19: =COUNTA('16_Liquidaciones'!A2:A1000) -> 18 | C19: =COUNTIF('16_Liquidaciones'!I2:I1000,"Pasa") -> 0 | D19: =COUNTIF('16_Liquidaciones'!I2:I1000,"Falla") -> 0 | E19: =COUNTIF('16_Liquidaciones'!I2:I1000,"Bloqueado") -> 0 | F19: =COUNTIF('16_Liquidaciones'!I2:I1000,"Pendiente")+COUNTBLANK('16_Liquidaciones'!I2:I1000)-COUNTBLANK('16_Liquidaciones'!A2:A1000) -> 18 | G19: =IF(B19=0,0,C19/B19) -> 0 | H19: =COUNTIFS('16_Liquidaciones'!G2:G1000,"Crítica",'16_Liquidaciones'!I2:I1000,"Falla") -> 0
A20: 17_Historial_Liq | B20: =COUNTA('17_Historial_Liq'!A2:A1000) -> 8 | C20: =COUNTIF('17_Historial_Liq'!I2:I1000,"Pasa") -> 0 | D20: =COUNTIF('17_Historial_Liq'!I2:I1000,"Falla") -> 0 | E20: =COUNTIF('17_Historial_Liq'!I2:I1000,"Bloqueado") -> 0 | F20: =COUNTIF('17_Historial_Liq'!I2:I1000,"Pendiente")+COUNTBLANK('17_Historial_Liq'!I2:I1000)-COUNTBLANK('17_Historial_Liq'!A2:A1000) -> 8 | G20: =IF(B20=0,0,C20/B20) -> 0 | H20: =COUNTIFS('17_Historial_Liq'!G2:G1000,"Crítica",'17_Historial_Liq'!I2:I1000,"Falla") -> 0
A21: 18_Conciliacion | B21: =COUNTA('18_Conciliacion'!A2:A1000) -> 12 | C21: =COUNTIF('18_Conciliacion'!I2:I1000,"Pasa") -> 0 | D21: =COUNTIF('18_Conciliacion'!I2:I1000,"Falla") -> 0 | E21: =COUNTIF('18_Conciliacion'!I2:I1000,"Bloqueado") -> 0 | F21: =COUNTIF('18_Conciliacion'!I2:I1000,"Pendiente")+COUNTBLANK('18_Conciliacion'!I2:I1000)-COUNTBLANK('18_Conciliacion'!A2:A1000) -> 12 | G21: =IF(B21=0,0,C21/B21) -> 0 | H21: =COUNTIFS('18_Conciliacion'!G2:G1000,"Crítica",'18_Conciliacion'!I2:I1000,"Falla") -> 0
A22: 19_Sesion_Web | B22: =COUNTA('19_Sesion_Web'!A2:A1000) -> 6 | C22: =COUNTIF('19_Sesion_Web'!I2:I1000,"Pasa") -> 0 | D22: =COUNTIF('19_Sesion_Web'!I2:I1000,"Falla") -> 0 | E22: =COUNTIF('19_Sesion_Web'!I2:I1000,"Bloqueado") -> 0 | F22: =COUNTIF('19_Sesion_Web'!I2:I1000,"Pendiente")+COUNTBLANK('19_Sesion_Web'!I2:I1000)-COUNTBLANK('19_Sesion_Web'!A2:A1000) -> 6 | G22: =IF(B22=0,0,C22/B22) -> 0 | H22: =COUNTIFS('19_Sesion_Web'!G2:G1000,"Crítica",'19_Sesion_Web'!I2:I1000,"Falla") -> 0
A23: TOTALES | B23: =SUM(B5:B22) -> 403 | C23: =SUM(C5:C22) -> 53 | D23: =SUM(D5:D22) -> 4 | E23: =SUM(E5:E22) -> 1 | F23: =SUM(F5:F22) -> 321 | G23: =IF(B23=0,0,C23/B23) -> 0.13151365 | H23: =SUM(H5:H22) -> 0
A25: 2. CONTEO POR PRIORIDAD
A26: Prioridad | B26: Total | C26: Pasa | D26: Falla | E26: Bloqueado | F26: Pendiente
A27: Crítica | B27: =SUMPRODUCT(COUNTIF(INDIRECT("'"&$A$5:$A$22&"'!G2:G1000"),"Crítica")) -> 113 | C27: =SUMPRODUCT(COUNTIFS(INDIRECT("'"&$A$5:$A$22&"'!G2:G1000"),"Crítica",INDIRECT("'"&$A$5:$A$22&"'!I2:I1000"),"Pasa")) -> 19 | D27: =SUMPRODUCT(COUNTIFS(INDIRECT("'"&$A$5:$A$22&"'!G2:G1000"),"Crítica",INDIRECT("'"&$A$5:$A$22&"'!I2:I1000"),"Falla")) -> 0 | E27: =SUMPRODUCT(COUNTIFS(INDIRECT("'"&$A$5:$A$22&"'!G2:G1000"),"Crítica",INDIRECT("'"&$A$5:$A$22&"'!I2:I1000"),"Bloqueado")) -> 0 | F27: =B27-C27-D27-E27 -> 94
A28: Alta | B28: =SUMPRODUCT(COUNTIF(INDIRECT("'"&$A$5:$A$22&"'!G2:G1000"),"Alta")) -> 157 | C28: =SUMPRODUCT(COUNTIFS(INDIRECT("'"&$A$5:$A$22&"'!G2:G1000"),"Alta",INDIRECT("'"&$A$5:$A$22&"'!I2:I1000"),"Pasa")) -> 18 | D28: =SUMPRODUCT(COUNTIFS(INDIRECT("'"&$A$5:$A$22&"'!G2:G1000"),"Alta",INDIRECT("'"&$A$5:$A$22&"'!I2:I1000"),"Falla")) -> 2 | E28: =SUMPRODUCT(COUNTIFS(INDIRECT("'"&$A$5:$A$22&"'!G2:G1000"),"Alta",INDIRECT("'"&$A$5:$A$22&"'!I2:I1000"),"Bloqueado")) -> 1 | F28: =B28-C28-D28-E28 -> 136
A29: Media | B29: =SUMPRODUCT(COUNTIF(INDIRECT("'"&$A$5:$A$22&"'!G2:G1000"),"Media")) -> 97 | C29: =SUMPRODUCT(COUNTIFS(INDIRECT("'"&$A$5:$A$22&"'!G2:G1000"),"Media",INDIRECT("'"&$A$5:$A$22&"'!I2:I1000"),"Pasa")) -> 13 | D29: =SUMPRODUCT(COUNTIFS(INDIRECT("'"&$A$5:$A$22&"'!G2:G1000"),"Media",INDIRECT("'"&$A$5:$A$22&"'!I2:I1000"),"Falla")) -> 2 | E29: =SUMPRODUCT(COUNTIFS(INDIRECT("'"&$A$5:$A$22&"'!G2:G1000"),"Media",INDIRECT("'"&$A$5:$A$22&"'!I2:I1000"),"Bloqueado")) -> 0 | F29: =B29-C29-D29-E29 -> 82
A30: Baja | B30: =SUMPRODUCT(COUNTIF(INDIRECT("'"&$A$5:$A$22&"'!G2:G1000"),"Baja")) -> 36 | C30: =SUMPRODUCT(COUNTIFS(INDIRECT("'"&$A$5:$A$22&"'!G2:G1000"),"Baja",INDIRECT("'"&$A$5:$A$22&"'!I2:I1000"),"Pasa")) -> 3 | D30: =SUMPRODUCT(COUNTIFS(INDIRECT("'"&$A$5:$A$22&"'!G2:G1000"),"Baja",INDIRECT("'"&$A$5:$A$22&"'!I2:I1000"),"Falla")) -> 0 | E30: =SUMPRODUCT(COUNTIFS(INDIRECT("'"&$A$5:$A$22&"'!G2:G1000"),"Baja",INDIRECT("'"&$A$5:$A$22&"'!I2:I1000"),"Bloqueado")) -> 0 | F30: =B30-C30-D30-E30 -> 33
A32: 3. COBERTURA
A33: Casos totales: | B33: =B23 -> 403
A34: Casos ejecutados: | B34: =C23+D23+E23 -> 58
A35: % Cobertura: | B35: =IF(B33=0,0,B34/B33) -> 0.1439206
A37: 4. FALLAS BLOQUEANTES DE RELEASE
A38: Total fallas críticas: | B38: =H23 -> 0
A39: Estado: | B39: =IF(B38=0,"LISTO PARA RELEASE","BLOQUEADO - Corregir fallas críticas") -> LISTO PARA RELEASE

Sheet 01_auth_users
A1: ID | B1: Módulo | C1: Título | D1: Precondiciones | E1: Pasos | F1: Resultado esperado | G1: Prioridad | H1: Tipo | I1: Resultado | J1: Notas
A2: AU-H-01 | B2: 01 Auth Users | C2: Landing pública | D2: Sin sesión | E2: 1. Abrir la app | F2: WelcomeScreen con "Agendar Cita", "Especialistas", "Explorar Servicios" | G2: Media | H2: Real | I2: Pasa
A3: AU-H-02 | B3: 01 Auth Users | C3: Registro de paciente | D3: Sin sesión | E3: 1. "Agendar Cita" → `/login` 2. Rol Paciente → registro 3. Nombre, email válido, contraseña ≥6 4. Enviar | F3: Diálogo de confirmación de correo (`AuthEmailConfirmationSent`); perfil creado con `activo=false`, rol Paciente | G3: Crítica | H3: Real | I3: Pasa
A4: AU-H-03 | B4: 01 Auth Users | C4: Confirmación de correo | D4: Registro recién hecho | E4: 1. Abrir el correo 2. Confirmar | F4: Cuenta confirmada; login posible. **Nota (2026-08-17)**: el link usa PKCE y el code verifier queda en el mismo browser donde se registró; ya no se borra al cerrar la pestaña, así que confirma aunque haya una sesión previa. Si el enlace se abre desde otro browser/dispositivo no se puede usar: la app lo avisa y sugiere iniciar sesión o reenviar. | G4: Crítica | H4: Real | I4: Pasa
A5: AU-H-04 | B5: 01 Auth Users | C5: Login de paciente confirmado | D5: Cuenta confirmada | E5: 1. `/login` 2. Paciente → signIn 3. Email + contraseña correctos | F5: `AuthAuthenticated`; redirección por rol (paciente sin perfil completo → `/complete-profile`; completo → `/services`) | G5: Crítica | H5: Real | I5: Pasa
A6: AU-H-05 | B6: 01 Auth Users | C6: Login de especialista | D6: `esp.aprobado` | E6: 1. Login con credenciales de especialista | F6: Redirección a `/specialist` | G6: Crítica | H6: Real | I6: Pasa
A7: AU-H-06 | B7: 01 Auth Users | C7: Login de admin | D7: `admin@test` | E7: 1. Login con credenciales de admin | F7: Redirección a `/admin` | G7: Crítica | H7: Real | I7: Pasa
A8: AU-H-07 | B8: 01 Auth Users | C8: Restaurar sesión al arrancar | D8: Sesión activa previa | E8: 1. Cerrar la app 2. Reabrir | F8: `checkCurrentSession` restaura; no pasa por login | G8: Alta | H8: Real | I8: Pasa
A9: AU-H-08 | B9: 01 Auth Users | C9: Editar perfil | D9: Sesión activa | E9: 1. `/profile` 2. Editar nombre y teléfono 3. Guardar | F9: `updateProfile` éxito; datos actualizados al recargar | G9: Alta | H9: Real | I9: Pasa | J9: Colocar flecha vista anterior
A10: AU-H-09 | B10: 01 Auth Users | C10: Cambio de contraseña | D10: Sesión activa | E10: 1. `/change-password` 2. Actual correcta, nueva ≥6, confirmación igual 3. Enviar | F10: Cambio exitoso; perfil recargado | G10: Alta | H10: Real | I10: Pasa | J10: Colocar flecha vista anterior
A11: AU-H-10 | B11: 01 Auth Users | C11: Recuperación de contraseña | D11: Cuenta confirmada | E11: 1. `/login` → "¿Olvidaste tu contraseña?" 2. Email 3. Abrir deep link del correo 4. Nueva contraseña + confirmación | F11: `resetPassword` envía correo; `completePasswordReset` actualiza y cierra la sesión temporal (`AuthPasswordChanged`); login con la nueva contraseña funciona | G11: Crítica | H11: Real
A12: AU-H-11 | B12: 01 Auth Users | C12: Logout con red | D12: Sesión activa | E12: 1. `/profile` 2. Cerrar sesión | F12: `signOut` completa; estado `AuthUnauthenticated`; navegación a `/` | G12: Alta | H12: Real | I12: Pasa
A13: AU-H-12 | B13: 01 Auth Users | C13: Deep link de registro | D13: Sin sesión | E13: 1. Abrir `…/login?registro=paciente` | F13: LoginScreen abre directamente el alta de paciente | G13: Media | H13: Real | I13: Pasa
A14: AU-V-01 | B14: 01 Auth Users | C14: Email sin `@` en registro | D14: Formulario de registro | E14: 1. Email `abc.com` 2. Enviar | F14: Validator rechaza; no hay llamada al servidor | G14: Alta | H14: Real | I14: Pasa
A15: AU-V-02 | B15: 01 Auth Users | C15: Contraseña <6 en registro | D15: Formulario de registro | E15: 1. Contraseña `12345` 2. Enviar | F15: Validator rechaza | G15: Alta | H15: Real | I15: Pasa
A16: AU-V-03 | B16: 01 Auth Users | C16: Nombre vacío en registro | D16: Formulario de registro | E16: 1. Nombre en blanco 2. Enviar | F16: Validator exige nombre | G16: Media | H16: Real | I16: Pasa
A17: AU-V-04 | B17: 01 Auth Users | C17: Registro de email duplicado | D17: Email ya registrado | E17: 1. Registrar el mismo email | F17: Mensaje de error claro del servidor; sin crash | G17: Alta | H17: Real | I17: Pasa
A18: AU-V-05 | B18: 01 Auth Users | C18: Login con contraseña incorrecta | D18: Cuenta confirmada | E18: 1. signIn con contraseña errónea | F18: `AuthError` con mensaje; sin crash | G18: Alta | H18: Real | I18: Pasa
A19: AU-V-06 | B19: 01 Auth Users | C19: Login de usuario inexistente | D19: — | E19: 1. signIn con email no registrado | F19: Mensaje de error; sin crash | G19: Media | H19: Real | I19: Pasa
A20: AU-V-07 | B20: 01 Auth Users | C20: Login con email no confirmado | D20: Registro sin confirmar | E20: 1. signIn | F20: Diálogo `email_not_confirmed` con opción de reenvío | G20: Alta | H20: Real | I20: Pendiente
A21: AU-V-08 | B21: 01 Auth Users | C21: Cambio de contraseña: actual incorrecta | D21: Sesión activa | E21: 1. `/change-password` 2. Actual errónea | F21: Error mostrado; contraseña sin cambiar | G21: Alta | H21: Real | I21: Falla | J21: cambia contraseña con actual incorrecta
A22: AU-V-09 | B22: 01 Auth Users | C22: Cambio: nueva <6 | D22: Sesión activa | E22: 1. Nueva `12345` | F22: Validator rechaza | G22: Media | H22: Real | I22: Pasa
A23: AU-V-10 | B23: 01 Auth Users | C23: Cambio: confirmación no coincide | D23: Sesión activa | E23: 1. Nueva ≠ confirmación | F23: Validator rechaza | G23: Media | H23: Real | I23: Pasa
A24: AU-V-11 | B24: 01 Auth Users | C24: Recuperación: confirmación no coincide | D24: Deep link abierto | E24: 1. Passwords distintos en ResetPasswordScreen | F24: Validator rechaza | G24: Media | H24: Real | I24: Pasa
A25: AU-V-12 | B25: 01 Auth Users | C25: Admin sin signUp | D25: `/login` | E25: 1. Rol Administrador | F25: No hay opción de registro ("acceso por invitación") | G25: Media | H25: Real | I25: Pasa
A26: AU-G-01 | B26: 01 Auth Users | C26: Sin sesión a ruta privada | D26: Sin sesión | E26: 1. Navegar a `/profile` (deep link) | F26: Redirect a `/` | G26: Alta | H26: Real | I26: Pasa
A27: AU-G-02 | B27: 01 Auth Users | C27: Sin sesión a `/admin` | D27: Sin sesión | E27: 1. Deep link `/admin` | F27: Redirect a `/` | G27: Crítica | H27: Real | I27: Pasa
A28: AU-G-03 | B28: 01 Auth Users | C28: Paciente a `/admin` | D28: Sesión de paciente | E28: 1. Deep link `/admin` | F28: Redirect por rol (a `/services`) | G28: Crítica | H28: Real | I28: Pasa
A29: AU-G-04 | B29: 01 Auth Users | C29: Paciente a `/specialist` | D29: Sesión de paciente | E29: 1. Deep link `/specialist` | F29: Redirect por rol | G29: Crítica | H29: Real | I29: Pasa
A30: AU-G-05 | B30: 01 Auth Users | C30: Especialista a `/admin` | D30: Sesión de especialista | E30: 1. Deep link `/admin` | F30: Redirect a `/specialist` | G30: Crítica | H30: Real | I30: Pasa
A31: AU-G-06 | B31: 01 Auth Users | C31: No-paciente a `/complete-profile` | D31: Sesión de especialista | E31: 1. Deep link `/complete-profile` | F31: Redirect por rol | G31: Alta | H31: Real | I31: Pendiente
A32: AU-G-07 | B32: 01 Auth Users | C32: Logueado visita `/login` | D32: Sesión activa | E32: 1. Navegar a `/login` | F32: Redirect inmediato por rol (Admin→`/admin`, Especialista→`/specialist`, Paciente→`/services`) | G32: Media | H32: Real | I32: Pasa
A33: AU-G-08 | B33: 01 Auth Users | C33: Especialista desactivado | D33: `esp.desactivado` (`activo=false`) | E33: 1. Login 2. Navegar cualquier ruta | F33: Guard fuerza `signOut` + redirect a `/` | G33: Crítica | H33: Real | I33: Pasa
A34: AU-G-09 | B34: 01 Auth Users | C34: Admin desactivado | D34: Admin con `activo=false` | E34: 1. Login 2. Navegar | F34: Logout forzado | G34: Alta | H34: Real | I34: Pendiente
A35: AU-G-10 | B35: 01 Auth Users | C35: Paciente desactivado | D35: `pac.desactivado` | E35: 1. Login 2. Intentar `/services` | F35: Solo puede estar en `/complete-profile`, `/face-map-questionnaire`, `/services`, `/auth/reset-password`; el resto → `/complete-profile` | G35: Alta | H35: Real | I35: Falla | J35: Verificar si `/services` está realmente permitido para desactivados
A36: AU-G-11 | B36: 01 Auth Users | C36: Rutas públicas sin sesión | D36: Sin sesión | E36: 1. Visitar `/`, `/services`, `/face-map-questionnaire`, `/auth/reset-password` | F36: Accesibles sin redirect | G36: Media | H36: Real | I36: Falla
A37: AU-E-01 | B37: 01 Auth Users | C37: Ciclo de estados de login | D37: Sin sesión | E37: 1. signIn válido | F37: Secuencia `AuthLoading` → `AuthAuthenticated(profile)`; sin estados de error intermedios | G37: Media | H37: Real | I37: Pasa
A38: AU-E-02 | B38: 01 Auth Users | C38: `refreshProfile` tras edición | D38: Sesión activa | E38: 1. `updateProfile` | F38: Perfil recargado sin pantalla de loading completa | G38: Baja | H38: Real | I38: Pasa
A39: AU-E-03 | B39: 01 Auth Users | C39: Aviso de cuenta pendiente | D39: Perfil con `activo=false` | E39: 1. Abrir `/profile` | F39: Aviso "Cuenta pendiente de activación" visible | G39: Media | H39: Real
A40: AU-E-04 | B40: 01 Auth Users | C40: `AuthPasswordChanged` tras reset | D40: Deep link recovery | E40: 1. Completar reset | F40: Estado emitido; sesión temporal cerrada; navegación a login | G40: Alta | H40: Real
A41: AU-E-05 | B41: 01 Auth Users | C41: `detached` limpia sesión local | D41: Sesión activa | E41: 1. Cerrar app hasta `detached` | F41: **Cambiado (2026-08-17)**: web elimina solo el token de sesión (localStorage) y conserva el code verifier PKCE para enlaces pendientes; mobile conserva el signOut local de gotrue (sesión + verifier) | G41: Media | H41: Real | I41: Pasa
A42: AU-N-01 | B42: 01 Auth Users | C42: ⚑ Logout sin red | D42: Sesión activa, modo avión | E42: 1. Cerrar sesión | F42: La sesión local se limpia igualmente (try/catch del datasource); navegación a `/` sin `AuthError` | G42: Crítica | H42: Real | I42: Pasa
A43: AU-N-02 | B43: 01 Auth Users | C43: Login sin red | D43: Modo avión | E43: 1. signIn | F43: `ServerFailure` → `AuthError` con mensaje; sin crash | G43: Alta | H43: Real | I43: Pasa
A44: AU-N-03 | B44: 01 Auth Users | C44: `.env` incompleto | D44: Sin `SUPABASE_URL` | E44: 1. Arrancar la app | F44: `AppEnv.validate()` lanza `StateError`; pantalla de error controlada (`_ErrorApp`) | G44: Media | H44: Real
A45: AU-N-04 | B45: 01 Auth Users | C45: FCM sin Firebase configurado | D45: Sesión activa | E45: 1. Autenticarse | F45: Registro FCM degrada sin crash; el flujo continúa | G45: Media | H45: Real
A46: AU-N-05 | B46: 01 Auth Users | C46: FCM con Firebase | D46: Sesión activa | E46: 1. Autenticarse | F46: Token registrado/upsert en `dispositivos_usuario` (onConflict `token_fcm`) | G46: Baja | H46: Real
A47: AU-N-06 | B47: 01 Auth Users | C47: Token expirado al arrancar | D47: Sesión vieja | E47: 1. Dejar expirar refresh token 2. Reabrir | F47: Auto-refresh o `AuthUnauthenticated`; nunca sesión zombie | G47: Alta | H47: Real | I47: Pasa
A48: AU-S-01 | B48: 01 Auth Users | C48: Logout fantasma en ProfileScreen | D48: Sesión activa, perfil en modo no-edición | E48: 1. Abrir `/profile` sin editar 2. Pulsar el botón de logout | F48: **RESUELTO (2026-08-14)**: el botón ahora ejecuta `AuthCubit.signOut()`; navega a `/login` vía BlocListener. Verificar que cierra sesión realmente | G48: Crítica | H48: Real | I48: Pasa
A49: AU-S-02 | B49: 01 Auth Users | C49: Fallback de nombre vacío | D49: Registro | E49: 1. Registrar con nombre vacío si el validator lo permite | F49: El fallback usa la parte local del email; verificar que no cree perfiles con nombre `null` | G49: Baja | H49: Real | I49: Pasa
A50: AU-S-03 | B50: 01 Auth Users | C50: `createProfile` tolerante | D50: Registro nuevo | E50: 1. Registrar paciente y especialista | F50: Paciente nace `activo=false`; especialista/admin `activo=true`; los upserts con fallback nunca lanzan | G50: Alta | H50: Real

Sheet 02_specialists
A1: ID | B1: Módulo | C1: Título | D1: Precondiciones | E1: Pasos | F1: Resultado esperado | G1: Prioridad | H1: Tipo | I1: Resultado | J1: Notas
A2: SP-H-01 | B2: 02 Specialists | C2: Onboarding completo | D2: `esp.nuevo` logueado | E2: 1. Entrar a `/specialist` 2. Paso 1: nombre, teléfono, tarifa, dirección (geocoding + mapa) 3. Paso 2: médico regente activo, ≥1 especialidad 4. Enviar | F2: `createSpecialist` + `guardarEspecialidades` + `saveLocation` (EWKT `SRID=4326;POINT(lng lat)`); navega a documentos | G2: Crítica | H2: Real | I2: Pasa
A3: SP-H-02 | B3: 02 Specialists | C3: Subida de documentos requeridos | D3: Perfil creado | E3: 1. `/specialist/documents` 2. Subir IDENTIFICACION 3. Subir LICENCIA | F3: Archivos en bucket `documentos-especialistas` (`<espId>/<ts>.<ext>`); filas con `estado_revision=PENDIENTE`, `activo=true` | G3: Crítica | H3: Real | I3: Pasa
A4: SP-H-03 | B4: 02 Specialists | C4: Solicitar verificación | D4: Ambos documentos subidos | E4: 1. Pulsar "Continuar" | F4: `solicitarVerificacion` → estado `EN_REVISION`; navega al home | G4: Crítica | H4: Real | I4: Pasa
A5: SP-H-04 | B5: 02 Specialists | C5: Home del aprobado | D5: `esp.aprobado` | E5: 1. Entrar a `/specialist` | F5: Tarjetas: verificación APROBADO, perfil, disponibilidad, documentos, contrato; `_MapaPacientesCard` y `_MisCitasCard` visibles (aprobado + disponible) | G5: Alta | H5: Real | I5: Pasa
A6: SP-H-05 | B6: 02 Specialists | C6: Toggle de disponibilidad | D6: Home cargado | E6: 1. Activar/desactivar switch | F6: Upsert en disponibilidad + `especialistas.disponible` sincronizado | G6: Alta | H6: Real | I6: Pasa
A7: SP-H-06 | B7: 02 Specialists | C7: Firma de contrato | D7: Sin contrato firmado | E7: 1. `/specialist/contract` 2. Dibujar firma 3. Confirmar | F7: PNG en bucket `contratos`; `firmarContrato` con `metodo_firma=TOUCH`; `contrato.firmado=true` | G7: Crítica | H7: Real | I7: Pasa | J7: Falta texto de contrato
A8: SP-H-07 | B8: 02 Specialists | C8: Guardar ubicación | D8: Onboarding o perfil | E8: 1. Elegir punto en el mapa 2. Guardar | F8: `ubicaciones_especialista` con geometría EWKT correcta | G8: Alta | H8: Real | I8: Pasa
A9: SP-H-08 | B9: 02 Specialists | C9: Pull-to-refresh del home | D9: Home cargado | E9: 1. Deslizar hacia abajo | F9: `loadDashboard` recarga todo sin duplicar estado | G9: Baja | H9: Real | I9: Pasa
A10: SP-H-09 | B10: 02 Specialists | C10: Edición de perfil personal | D10: Perfil existente | E10: 1. `/specialist/profile` 2. Editar nombre/teléfono/dirección/tarifa 3. Guardar | F10: Actualiza `profiles` + datos personales; verificación intacta | G10: Media | H10: Real | I10: Pasa
A11: SP-H-10 | B11: 02 Specialists | C11: Edición de perfil profesional | D11: Perfil existente | E11: 1. Editar licencia/médico regente/especialidades 2. Guardar | F11: `actualizarDatosProfesionales` + `guardarEspecialidades` (reemplaza conjunto: delete+insert) | G11: Alta | H11: Real | I11: Pasa
A12: SP-V-01 | B12: 02 Specialists | C12: Paso 1 con campos vacíos | D12: Onboarding | E12: 1. Dejar nombre/teléfono/dirección vacíos 2. Continuar | F12: Validators bloquean el paso | G12: Alta | H12: Real
A13: SP-V-02 | B13: 02 Specialists | C13: Paso 2 sin especialidades | D13: Onboarding paso 2 | E13: 1. Sin seleccionar especialidad 2. Enviar | F13: Snackbar exigiendo ≥1 especialidad; no se guarda | G13: Alta | H13: Real
A14: SP-V-03 | B14: 02 Specialists | C14: Médico regente obligatorio | D14: Onboarding paso 2 | E14: 1. Dropdown vacío 2. Enviar | F14: Validator obliga a seleccionar | G14: Alta | H14: Real | I14: Pasa
A15: SP-V-04 | B15: 02 Specialists | C15: Dropdown solo muestra activos | D15: Médicos regentes con uno PENDIENTE | E15: 1. Abrir dropdown | F15: Solo aparecen ACTIVOS | G15: Media | H15: Real
A16: SP-V-05 | B16: 02 Specialists | C16: Nuevo médico regente | D16: Onboarding paso 2 | E16: 1. Diálogo "registrar médico regente" 2. Datos válidos | F16: Creado con `PENDIENTE`/`activo=false`; queda seleccionado pero no cuenta como válido hasta aprobación admin | G16: Alta | H16: Real | I16: Bloqueado | J16: postgrestexception: ´code: 42501 policy for table medicos_regentes, hint: NULL
A17: SP-V-06 | B17: 02 Specialists | C17: Firma vacía | D17: `/specialist/contract` | E17: 1. Sin dibujar nada 2. Confirmar | F17: Validación impide firmar | G17: Media | H17: Real | I17: Pasa
A18: SP-V-07 | B18: 02 Specialists | C18: Subida de archivo inválido | D18: Documentos | E18: 1. Archivo corrupto o extensión extraña | F18: Error controlado por snackbar; sin crash | G18: Media | H18: Real | I18: Falla | J18: No permite subir otro: identificacion-Licencia-Diploma
A19: SP-V-08 | B19: 02 Specialists | C19: "Continuar" deshabilitado | D19: Falta IDENTIFICACION o LICENCIA | E19: 1. Observar el botón | F19: Deshabilitado hasta tener ambos requeridos | G19: Alta | H19: Real | I19: Pasa
A20: SP-G-01 | B20: 02 Specialists | C20: Paciente a rutas de especialista | D20: Sesión de paciente | E20: 1. Deep link `/specialist`, `/specialist/documents`, `/specialist/contract` | F20: Redirect por rol | G20: Crítica | H20: Real | I20: Pasa | J20: No emite ningún mensaje que indique el error: "No es un especialista. Pasa a Servicios paiente".
A21: SP-G-02 | B21: 02 Specialists | C21: Sin sesión a `/specialist` | D21: Sin sesión | E21: 1. Deep link | F21: Redirect a `/` | G21: Alta | H21: Real | I21: Pasa
A22: SP-G-03 | B22: 02 Specialists | C22: Dueño no puede auto-aprobarse | D22: `esp.revision` | E22: 1. Intentar update directo de `estado_verificacion` (vía cliente/consola) | F22: Trigger `trg_proteger_verificacion_especialista` lo impide; el dueño solo INSERT en PENDIENTE y autosolicitud `PENDIENTE/RECHAZADO → EN_REVISION` | G22: Crítica | H22: Real | I22: Pasa | J22: No emite ningún mensaje que indique el error: "No es un administrador. Pasa a datos especialista".
A23: SP-G-04 | B23: 02 Specialists | C23: Dueño no puede revisar sus documentos | D23: `esp.revision` | E23: 1. Intentar update de `estado_revision`/`revisado_por` | F23: Trigger `trg_proteger_revision_documento` lo impide | G23: Crítica | H23: Real | I23: Pasa
A24: SP-G-05 | B24: 02 Specialists | C24: RLS de documentos | D24: `esp.nuevo` | E24: 1. Listar documentos propios | F24: Solo ve sus propios documentos | G24: Alta | H24: Real
A25: SP-E-01 | B25: 02 Specialists | C25: Redirect sin perfil | D25: Especialista sin registro | E25: 1. Entrar a `/specialist` | F25: BlocListener redirige a onboarding con `extra:''` | G25: Crítica | H25: Real
A26: SP-E-02 | B26: 02 Specialists | C26: Redirect sin datos profesionales | D26: Perfil sin médico regente o sin especialidades | E26: 1. Entrar a `/specialist` | F26: Redirect a onboarding con id | G26: Alta | H26: Real
A27: SP-E-03 | B27: 02 Specialists | C27: Redirect por documentos faltantes | D27: Perfil completo, sin IDENTIFICACION/LICENCIA activos | E27: 1. Entrar a `/specialist` | F27: Redirect a documentos | G27: Alta | H27: Real
A28: SP-E-04 | B28: 02 Specialists | C28: Rechazado no es redirigido | D28: `esp.rechazado` con docs faltantes | E28: 1. Entrar a `/specialist` | F28: Se queda en el home para leer el motivo (excepción del redirect) | G28: Alta | H28: Real
A29: SP-E-05 | B29: 02 Specialists | C29: Motivo de rechazo visible | D29: `esp.rechazado` | E29: 1. Ver `_VerificationCard` | F29: Estado RECHAZADO + observación en rojo + botón "Corregir y reenviar" | G29: Alta | H29: Real
A30: SP-E-06 | B30: 02 Specialists | C30: Reenvío tras rechazo | D30: `esp.rechazado` | E30: 1. Corregir documentos 2. "Corregir y reenviar" | F30: `solicitarVerificacion` → `EN_REVISION` de nuevo | G30: Crítica | H30: Real
A31: SP-E-07 | B31: 02 Specialists | C31: Documento rechazado exige re-subida | D31: Documento con `estado_revision=RECHAZADO` (`activo=false`) | E31: 1. Entrar al home | F31: El home vuelve a exigir el documento (cuenta como no subido); re-subir crea nueva fila | G31: Alta | H31: Real
A32: SP-E-08 | B32: 02 Specialists | C32: Bloqueado | D32: `esp.bloqueado` | E32: 1. Entrar a `/specialist` | F32: Estado BLOQUEADO con observación visible; sin acceso a mapa/citas | G32: Alta | H32: Real
A33: SP-E-09 | B33: 02 Specialists | C33: Transiciones válidas de verificación | D33: Distintos estados | E33: 1. Verificar matriz: PENDIENTE→EN_REVISION (dueño); EN_REVISION→APROBADO/RECHAZADO (admin); APROBADO→BLOQUEADO (admin) | F33: Solo el rol autorizado dispara cada transición | G33: Crítica | H33: Real
A34: SP-E-10 | B34: 02 Specialists | C34: Presencia heartbeat | D34: Sesión de especialista | E34: 1. Mantener app abierta 60+ s | F34: `en_linea=true`, `ultima_conexion` actualizada cada ~60 s | G34: Media | H34: Real
A35: SP-E-11 | B35: 02 Specialists | C35: Offline al pausar | D35: Sesión de especialista | E35: 1. Enviar app a segundo plano | F35: Marca offline al pausar; limpia sesión local en `detached` | G35: Media | H35: Real
... A45: SP-S-05 | B45: 02 Specialists | C45: Disponibilidad sin ubicación | D45: Sin `ubicaciones_especialista` | E45: 1. Activar disponibilidad | F45: No rompe; el mapa luego no tendrá punto propio | G45: Media | H45: Real

Sheet 03_admin_config
A1: ID | B1: Módulo | C1: Título | D1: Precondiciones | E1: Pasos | F1: Resultado esperado | G1: Prioridad | H1: Tipo | I1: Resultado | J1: Notas
A2: AC-H-01 | B2: 03 Admin Config | C2: Carga del panel | D2: Admin logueado | E2: 1. Entrar a `/admin` | F2: `loadAllEspecialistas()`: lista con badge de estado, licencia, fecha de solicitud; documentos por especialista; médicos regentes | G2: Crítica | H2: Real
A3: AC-H-02 | B3: 03 Admin Config | C3: Aprobar especialista | D3: `esp.revision` | E3: 1. Pulsar "Aprobar" | F3: `updateVerificacion` → `APROBADO`, `activo=true`, `aprobadoPor`=id del admin, fechas; observación limpiada | G3: Crítica | H3: Real
A4: AC-H-03 | B4: 03 Admin Config | C4: Rechazar con motivo | D4: `esp.revision` | E4: 1. "Rechazar" 2. Escribir motivo 3. Confirmar | F4: `RECHAZADO` + observación guardada; el especialista ve el motivo en su home | G4: Crítica | H4: Real
A5: AC-H-04 | B5: 03 Admin Config | C5: Bloquear con motivo | D5: `esp.aprobado` | E5: 1. "Bloquear" 2. Motivo 3. Confirmar | F5: `BLOQUEADO` + observación; especialista pierde acceso al marketplace | G5: Crítica | H5: Real
A6: AC-H-05 | B6: 03 Admin Config | C6: Ver documento | D6: Documento con adjunto | E6: 1. Pulsar "Ver" | F6: `url_launcher` abre la URL del archivo | G6: Media | H6: Real
A7: AC-H-06 | B7: 03 Admin Config | C7: Aprobar documento | D7: Documento EN_REVISION | E7: 1. "Aprobar documento" | F7: `revisarDocumento` → `APROBADO`, `activo=true`, `revisado_por`, `fecha_revision` | G7: Alta | H7: Real
A8: AC-H-07 | B8: 03 Admin Config | C8: Rechazar documento | D8: Documento EN_REVISION | E8: 1. "Rechazar documento" 2. Motivo | F8: `RECHAZADO` + `observacion_revision` + `activo=false` | G8: Alta | H8: Real
A9: AC-H-08 | B9: 03 Admin Config | C9: Aprobar médico regente | D9: Médico PENDIENTE | E9: 1. "Aprobar médico regente" | F9: `aprobarMedicoRegente` → ACTIVO; aparece en dropdowns de onboarding | G9: Alta | H9: Real
A10: AC-H-09 | B10: 03 Admin Config | C10: Enlace a usuarios | D10: Panel cargado | E10: 1. Pulsar enlace a `/admin/usuarios` | F10: Navega correctamente | G10: Baja | H10: Real
A11: AC-V-01 | B11: 03 Admin Config | C11: Rechazo con motivo vacío | D11: Diálogo de motivo | E11: 1. Confirmar con texto vacío | F11: **Confirmar comportamiento**: el diálogo permite confirmar vacío → `observacion=null`; verificar qué ve el especialista (sin motivo) | G11: Alta | H11: Real
A12: AC-V-02 | B12: 03 Admin Config | C12: Motivo >500 caracteres | D12: Diálogo de motivo | E12: 1. Teclear 501 caracteres | F12: `maxLength 500` recorta; no se envía más | G12: Baja | H12: Real
A13: AC-V-03 | B13: 03 Admin Config | C13: Documento sin adjunto | D13: Fila sin archivo | E13: 1. Pulsar "Ver" | F13: Snackbar indicando que no hay adjunto; sin crash | G13: Media | H13: Real
... A30: AC-S-02 | B30: 03 Admin Config | C30: Bloqueo sin motivo | D30: Diálogo | E30: 1. Bloquear con motivo vacío | F30: `observacion=null`; especialista bloqueado sin explicación — decidir si es aceptable | G30: Media | H30: Real

Sheet 04_admin_users
A1: ID | B1: Módulo | C1: Título | D1: Precondiciones | E1: Pasos | F1: Resultado esperado | G1: Prioridad | H1: Tipo | I1: Resultado | J1: Notas
A2: AUU-H-01 | B2: 04 Admin Users | C2: Carga de usuarios | D2: Admin logueado | E2: 1. Entrar a `/admin/usuarios` | F2: Lista de profiles (email, full_name, phone, role, activo) ordenada por `created_at` | G2: Crítica | H2: Real
A3: AUU-H-02 | B3: 04 Admin Users | C3: Desactivar paciente | D3: Paciente activo | E3: 1. Apagar switch del paciente | F3: `setActivo(userId,false)`; lista recargada con el cambio | G3: Crítica | H3: Real
A4: AUU-H-03 | B4: 04 Admin Users | C4: Reactivar paciente | D4: `pac.desactivado` | E4: 1. Encender switch | F4: `activo=true`; el paciente vuelve a operar normal | G4: Alta | H4: Real
A5: AUU-H-04 | B5: 04 Admin Users | C5: Desactivar especialista | D5: Especialista activo | E5: 1. Apagar switch | F5: Éxito + recarga | G5: Crítica | H5: Real
A6: AUU-V-01 | B6: 04 Admin Users | C6: Sin usuarios | D6: BD sin profiles | E6: 1. Cargar | F6: Mensaje "No hay usuarios registrados." | G6: Baja | H6: Real
A7: AUU-V-02 | B7: 04 Admin Users | C7: `setActivo` falla | D7: Sin red | E7: 1. Toggle | F7: Snackbar de error; switch vuelve al estado previo tras recarga | G7: Alta | H7: Real
A8: AUU-G-01 | B8: 04 Admin Users | C8: No-admin a `/admin/usuarios` | D8: Sesión de paciente o especialista | E8: 1. Deep link | F8: Guard redirige por rol | G8: Crítica | H8: Real
A9: AUU-G-02 | B9: 04 Admin Users | C9: RLS select de profiles | D9: Paciente | E9: 1. Intentar leer la lista completa de profiles vía cliente | F9: Policies `profiles_admin_select` lo impiden (solo admin) | G9: Crítica | H9: Real
A10: AUU-G-03 | B10: 04 Admin Users | C10: RLS update de activo | D10: Paciente/especialista | E10: 1. Intentar `update` de `profiles.activo` ajeno | F10: `profiles_admin_update` lo impide | G10: Crítica | H10: Real
A11: AUU-G-04 | B11: 04 Admin Users | C11: Sin switch para admins | D11: Lista con otro admin | E11: 1. Observar fila de otro Administrador | F11: Sin switch (`canToggle=false` para rol Administrador) | G11: Alta | H11: Real
A12: AUU-G-05 | B12: 04 Admin Users | C12: Sin switch para sí mismo | D12: Admin logueado | E12: 1. Observar propia fila ("· tú") | F12: Sin switch; no puede desactivarse a sí mismo | G12: Alta | H12: Real
A13: AUU-E-01 | B13: 04 Admin Users | C13: ⚑ Desactivar especialista con sesión activa | D13: Especialista logueado en 2º dispositivo | E13: 1. Desactivar como admin 2. Navegar en el 2º dispositivo | F13: Guard `onDeactivated` fuerza `signOut` + redirect a `/` | G13: Crítica | H13: Real
... A20: AUU-S-02 | B20: 04 Admin Users | C20: Desactivar admin (laguna UI) | D20: Dos admins | E20: 1. Observar si la UI impide desactivar a OTRO admin | F20: La regla `canToggle` excluye admins; confirmar que no hay vía alternativa | G20: Media | H20: Real

Sheet 05_catalog_services
A1: ID | B1: Módulo | C1: Título | D1: Precondiciones | E1: Pasos | F1: Resultado esperado | G1: Prioridad | H1: Tipo | I1: Resultado | J1: Notas
A2: CS-H-01 | B2: 05 Catalog Services | C2: Catálogo público | D2: Sin sesión | E2: 1. Entrar a `/services` | F2: Categorías activas + servicios activos con join `categorias_servicio`; grid visible | G2: Crítica | H2: Real
A3: CS-H-02 | B3: 05 Catalog Services | C3: Filtrar por categoría | D3: Catálogo cargado | E3: 1. Pulsar chip de categoría | F3: Solo servicios de esa categoría | G3: Alta | H3: Real
A4: CS-H-03 | B4: 05 Catalog Services | C4: Volver a "Todos" | D4: Filtro activo | E4: 1. Pulsar "Todos" | F4: `selectCategoria(null)` restaura todo el catálogo | G4: Media | H4: Real
A5: CS-H-04 | B5: 05 Catalog Services | C5: Banner verde | D5: `pac.activo` | E5: 1. Entrar a `/services` | F5: Banner APROBADA y vigente (verde) | G5: Media | H5: Real
A6: CS-H-05 | B6: 05 Catalog Services | C6: Reserva con pago total | D6: `pac.activo`, servicio seleccionado | E6: 1. Seleccionar servicio 2. Modal "Cancelar Servicio" → "Cancelar Totalidad ($precio)" 3. Pagar | F6: `procesarPagoStripe(PAGO_TOTAL)` → `createServicePayment` → solicitud **PUBLICADA**; diálogo de éxito | G6: Crítica | H6: Real
A7: CS-H-06 | B7: 05 Catalog Services | C7: Reserva con depósito | D7: `pac.activo` | E7: 1. "Cancelar Depósito ($30)" 2. Pagar | F7: `procesarPagoStripe(DEPOSITO)` → solicitud **BORRADOR**; diálogo de éxito | G7: Crítica | H7: Real
A8: CS-V-01 | B8: 05 Catalog Services | C8: Selección sin sesión | D8: Sin sesión | E8: 1. Seleccionar servicio | F8: Diálogo "Regístrate como paciente" → `/login?registro=paciente` | G8: Alta | H8: Real
A9: CS-V-02 | B9: 05 Catalog Services | C9: Evaluación RECHAZADA | D9: `pac.rechazado` | E9: 1. Seleccionar servicio | F9: Modal bloqueado (RN-020/RN-022); no permite pagar | G9: Crítica | H9: Real
A10: CS-V-03 | B10: 05 Catalog Services | C10: Evaluación VENCIDA | D10: `pac.vencido` | E10: 1. Seleccionar servicio | F10: Modal de expiración con "Pagar $30 y Renovar" → `/complete-profile` | G10: Alta | H10: Real
A11: CS-V-04 | B11: 05 Catalog Services | C11: Evaluación PENDIENTE | D11: `pac.nuevo` | E11: 1. Seleccionar servicio | F11: Modal "Completar Evaluación" → `/complete-profile` | G11: Alta | H11: Real
A12: CS-V-05 | B12: 05 Catalog Services | C12: Pago cancelado | D12: `pac.activo` | E12: 1. Elegir pago 2. Cancelar PaymentSheet | F12: Flujo abortado; sin solicitud ni pago registrados | G12: Crítica | H12: Real
A13: CS-V-06 | B13: 05 Catalog Services | C13: Pago fallido | D13: Error de Stripe | E13: 1. Provocar fallo | F13: Snackbar de fallo de pago (distinto del de registro) | G13: Alta | H13: Real
... A28: CS-S-03 | B28: 05 Catalog Services | C28: `copyWith` de categoría | D28: Filtro activo | E28: 1. `selectCategoria(null)` | F28: Permite resetear a null (no usa `??`); comportamiento correcto | G28: Baja | H28: Real

Sheet 06_marketplace_citas
A1: ID | B1: Módulo | C1: Título | D1: Precondiciones | E1: Pasos | F1: Resultado esperado | G1: Prioridad | H1: Tipo | I1: Resultado | J1: Notas
A2: MK-H-01 | B2: 06 Marketplace Citas | C2: Carga del mapa | D2: `esp.aprobado` | E2: 1. Entrar a `/specialist/map` | F2: Carga dashboard + `MarketplaceCubit.load`: markers de solicitudes y especialistas aprobados; tarjeta de conteo | G2: Crítica | H2: Real
A3: MK-H-02 | B3: 06 Marketplace Citas | C3: Marker de paciente | D3: Mapa cargado | E3: 1. Tocar marker de solicitud | F3: Detalle del paciente | G3: Alta | H3: Real
A4: MK-H-03 | B4: 06 Marketplace Citas | C4: Orden por cercanía | D4: Varias solicitudes | E4: 1. "Por cercanía" | F4: Bottom sheet ordenado por distancia Haversine desde mi ubicación | G4: Alta | H4: Real
A5: MK-H-04 | B5: 06 Marketplace Citas | C5: Aceptar solicitud | D5: Solicitud vigente | E5: 1. Detalle → "Aceptar" | F5: RPC `aceptar_solicitud` → `aceptada`: se elimina de la lista; "¡El paciente es tuyo!"; cita creada | G5: Crítica | H5: Real
A6: MK-H-05 | B6: 06 Marketplace Citas | C6: Pull-to-refresh | D6: Mapa cargado | E6: 1. Deslizar | F6: Recarga solicitudes/especialistas | G6: Baja | H6: Real
A7: MK-H-06 | B7: 06 Marketplace Citas | C7: Recentrar y zoom | D7: Mapa cargado | E7: 1. FABs de recentrar/zoom | F7: Centran en mi ubicación / ajustan zoom | G7: Baja | H7: Real
A8: MK-V-01 | B8: 06 Marketplace Citas | C8: Acceso restringido | D8: `esp.revision` (no aprobado) | E8: 1. Entrar a `/specialist/map` | F8: `_AccesoRestringido`; sin mapa | G8: Crítica | H8: Real
A9: MK-V-02 | B9: 06 Marketplace Citas | C9: Solicitud expirada | D9: Solicitud con `fechaExpiracion` pasada | E9: 1. "Aceptar" | F9: RPC devuelve `expirada`: se elimina de la lista con aviso | G9: Alta | H9: Real
A10: MK-V-03 | B10: 06 Marketplace Citas | C10: Especialista no aprobado acepta | D10: Vía forzada (cliente manipulado) | E10: 1. Llamar RPC sin estar aprobado | F10: RPC devuelve `noAprobado`: "Solo especialistas verificados y activos…" | G10: Crítica | H10: Real
A11: MK-V-04 | B11: 06 Marketplace Citas | C11: Solicitud ya asignada | D11: Solicitud aceptada por otro | E11: 1. "Aceptar" | F11: `ASIGNADA`/`NO_ENCONTRADA`: "ya fue asignado" + refresco | G11: Alta | H11: Real
A12: MK-G-01 | B12: 06 Marketplace Citas | C12: Paciente a `/specialist/map` | D12: Sesión de paciente | E12: 1. Deep link | F12: Guard redirige por rol | G12: Crítica | H12: Real
A13: MK-G-02 | B13: 06 Marketplace Citas | C13: RPC con sesión de paciente | D13: Paciente | E13: 1. Invocar `obtener_solicitudes_publicadas_geo` | F13: RLS/security definer lo impide o devuelve vacío | G13: Alta | H13: Real
... A22: MK-N-04 | B22: 06 Marketplace Citas | C22: Una de las 3 consultas falla | D22: Fallo parcial | E22: 1. Provocar error en una consulta | F22: El primer error gana → estado de error; sin estado parcial corrupto | G22: Media | H22: Real
A23: MK-S-01 | B23: 06 Marketplace Citas | C23: ⚑ Concurrencia de aceptación | D23: 2 especialistas ante la misma solicitud | E23: 1. Ambos pulsan "Aceptar" casi a la vez | F23: "Primer aviso gana": uno recibe `aceptada`, el otro `ASIGNADA`; sin doble cita | G23: Crítica | H23: Real | I23: ✅ | J23: E2E ítems 10-11 (claim atómico)
A24: MK-S-02 | B24: 06 Marketplace Citas | C24: Fold que ignora failures | D24: Fallo de red en `aceptar` | E24: 1. Aceptar sin red | F24: **Confirmar bug**: `res.fold((f) => null, …)` no maneja el error; verificar si la UI queda sin feedback o bloqueada | G24: Alta | H24: Real | I24: ✅ | J24: **Corregido 2026-08-21**: `_refrescar` conserva el mapa y avisa "No se pudo actualizar el mapa: …"; test `marketplace_cubit_test` (MK-S-02)
A25: MK-S-03 | B25: 06 Marketplace Citas | C25: Getter `expirada` sin uso | D25: Solicitud expirada en lista | E25: 1. Observar si la UI marca expiradas antes del RPC | F25: El getter de la entidad no se usa; la expiración solo la decide el RPC al aceptar | G25: Baja | H25: Real | I25: ⬜ | J25: Pendiente de prueba específica
A26: MK-M-01 | B26: 06 Marketplace Citas | C26: Solicitud multi-servicio | D26: Solicitud con `solicitud_detalles` PUBLICADA | E26: 1. Ver detalle del paciente en el mapa | F26: Lista de servicios con cantidad y subtotal; total agregado | G26: Alta | H26: Real | I26: ✅ | J26: E2E ítem 1
A27: MK-M-02 | B27: 06 Marketplace Citas | C27: Preferencia de fecha | D27: Solicitud con `fecha_programada` | E27: 1. Ver detalle | F27: Muestra la fecha/hora preferida por el paciente | G27: Media | H27: Real | I27: ✅ | J27: E2E ítem 3
A28: MK-M-03 | B28: 06 Marketplace Citas | C28: Geofencing por radio | D28: 2 solicitudes, una fuera del radio configurado | E28: 1. Cargar el mapa | F28: Solo aparece la solicitud dentro del radio del especialista | G28: Crítica | H28: Real | I28: ✅ | J28: E2E ítem 7 (smoke2: solo especialistas del radio)
A29: MK-M-04 | B29: 06 Marketplace Citas | C29: Radio override por solicitud | D29: Solicitud con `radio_busqueda` propio | E29: 1. Cargar el mapa | F29: Se usa el radio de la solicitud si está definido | G29: Alta | H29: Real | I29: ⬜ | J29: Pendiente de prueba específica
A30: MK-M-05 | B30: 06 Marketplace Citas | C30: Notificación a otros | D30: 2 especialistas en el radio | E30: 1. Uno acepta la solicitud | F30: El otro recibe notificación in-app `SOLICITUD_ASIGNADA` | G30: Crítica | H30: Real | I30: ✅ | J30: E2E ítem 11 (smoke2: 2 usuarios)
A31: MK-M-06 | B31: 06 Marketplace Citas | C31: Dirección exacta revelada | D31: Cita asignada | E31: 1. Entrar a Mis Citas → detalle | F31: Se revela la dirección exacta (RLS `solicitud_especialista_asignado_select`) | G31: Crítica | H31: Real | I31: ✅ | J31: E2E ítem 12
A32: MK-M-07 | B32: 06 Marketplace Citas | C32: Historial SOLICITUD | D32: Solicitud creada/publicada/aceptada | E32: 1. Consultar `historial_estados` (tipo_entidad=SOLICITUD) | F32: Registra creaciones y cambios de estado | G32: Alta | H32: Real | I32: ✅ | J32: E2E ítem 14 (sin duplicados post-00500)

Sheet 07_patients_compliance
A1: ID | B1: Módulo | C1: Título | D1: Precondiciones | E1: Pasos | F1: Resultado esperado | G1: Prioridad | H1: Tipo | I1: Resultado | J1: Notas
A2: PC-H-01 | B2: 07 Patients Compliance | C2: Cuestionario real cargado | D2: Migración aplicada | E2: 1. Entrar al cuestionario desde complete-profile | F2: Se cargan las 10 preguntas del seed (SI_NO, TEXTO, LISTA, NUMERO, FECHA, MULTIPLE) con su versión; sin preguntas hardcodeadas | G2: Crítica | H2: Real
A3: PC-H-02 | B3: 07 Patients Compliance | C3: Enviar respuestas | D3: Formulario completo | E3: 1. Responder todas las obligatorias 2. "Enviar y Evaluar" | F3: RPC guarda `evaluaciones_salud` + `respuestas_salud` (con snapshot `pregunta_texto`); resultado APTO si no hay riesgos | G3: Crítica | H3: Real
A4: PC-H-03 | B4: 07 Patients Compliance | C4: Dictamen con riesgos | D4: Respuesta dispara sentinela (ej. alergia = Sí) | E4: 1. Responder Sí en alergia 2. Enviar | F4: Modal "Revisión requerida" con la etiqueta de riesgo; NO se abre Qualify | G4: Alta | H4: Real
A5: PC-H-04 | B5: 07 Patients Compliance | C5: Dictamen NO APTO | D5: Respuesta dispara sentinela crítico (embarazo = Sí) | E5: 1. Responder Sí en embarazo 2. Enviar | F5: Modal "NO APTO" con riesgo crítico; NO se registra validación | G5: Crítica | H5: Real
A6: PC-H-05 | B6: 07 Patients Compliance | C6: Qualify simulado con fechas reales | D6: Dictamen APTO | E6: 1. Elegir Telemedicina/Medicina Interna 2. Esperar ~3 s | F6: `registrar_validacion_telemedicina`: estado APROBADA, `fecha_validacion`=hoy, `fecha_vencimiento`=+365 días; modal muestra ambas fechas | G6: Crítica | H6: Real
A7: PC-H-06 | B7: 07 Patients Compliance | C7: Versión conservada | D7: Evaluación previa existente | E7: 1. Re-evaluar tras activar v2 | F7: La evaluación nueva usa la versión activa; las respuestas guardan el texto de la pregunta en el momento | G7: Alta | H7: Real
A8: PC-H-07 | B8: 07 Patients Compliance | C8: Estado de salud | D8: Sesión paciente | E8: 1. Abrir `/estado-salud` desde el catálogo (icono corazón) | F8: Muestra cuota, cuestionario, resultado, validación, vencimiento y siguiente paso | G8: Alta | H8: Real
A9: PC-V-01 | B9: 07 Patients Compliance | C9: Obligatorias sin responder | D9: Formulario | E9: 1. Dejar una obligatoria vacía 2. Enviar | F9: Error de validación por campo (chip/input) y snackbar naranja | G9: Alta | H9: Real
A10: PC-V-02 | B10: 07 Patients Compliance | C10: Número inválido | D10: Pregunta NUMERO | E10: 1. Escribir "abc" 2. Enviar | F10: Validator rechaza "Ingresa un valor numérico válido" | G10: Media | H10: Real
A11: PC-V-03 | B11: 07 Patients Compliance | C11: Sin cuestionario activo | D11: Config sin activa | E11: 1. Desactivar todas las versiones 2. Abrir cuestionario | F11: Pantalla de error con "Reintentar" | G11: Alta | H11: Real
A12: PC-V-04 | B12: 07 Patients Compliance | C12: Validación vencida (gate RN-020) | D12: Validación >365 días | E12: 1. Intentar reservar servicio con `requiere_telemedicina` | F12: `ValidarAccesoRN020` devuelve VENCIDA → modal de expiración | G12: Crítica | H12: Real
A13: PC-V-05 | B13: 07 Patients Compliance | C13: Validación rechazada | D13: `validaciones_telemedicina` RECHAZADA | E13: 1. Intentar reservar | F13: Modal "Reserva Bloqueada (RN-020/RN-022)" | G13: Crítica | H13: Real
... A29: PC-N-03 | B29: 07 Patients Compliance | C29: Sin preguntas configuradas | D29: Cuestionario vacío | E29: 1. Abrir cuestionario | F29: Formulario vacío con botón enviar deshabilitado (0/0) | G29: Media | H29: Real
A30: PC-S-01 | B30: 07 Patients Compliance | C30: Qualify simulado | G30: Baja | H30: Real
A31: PC-S-02 | B31: 07 Patients Compliance | C31: Legacy `SupabaseService` | G31: Baja | H31: Real
A32: PC-S-03 | B32: 07 Patients Compliance | C32: Edición de preguntas del catálogo | G32: Media | H32: Real

Sheet 08_payments_stripe
A1: ID | B1: Módulo | C1: Título | D1: Precondiciones | E1: Pasos | F1: Resultado esperado | G1: Prioridad | H1: Tipo | I1: Resultado | J1: Notas
A2: PS-H-01 | B2: 08 Payments Stripe | C2: Cuota inicial $30 | D2: Paciente en complete-profile | E2: 1. Pagar cuota | F2: `registerInitialPayment`: `profiles.payment_completed=true` + `pacientes.activo=true`; referencia guardada | G2: Crítica | H2: Real
A3: PS-H-02 | B3: 08 Payments Stripe | C3: Depósito de servicio | D3: Servicio seleccionado | E3: 1. Pagar depósito | F3: `createServicePayment`: solicitud BORRADOR + `pagos` (monto_total, depósito, saldo, PARCIAL) + `transacciones` (DEPÓSITO, APROBADO) | G3: Crítica | H3: Real
A4: PS-H-03 | B4: 08 Payments Stripe | C4: Pago total de servicio | D4: Servicio seleccionado | E4: 1. Pagar totalidad | F4: Solicitud **PUBLICADA** + pago PAGADO + transacción PAGO_TOTAL | G4: Crítica | H4: Real
A5: PS-H-04 | B5: 08 Payments Stripe | C5: Cobro de saldo | D5: Cita con `saldo_pendiente>0` | E5: 1. Finalizar tratamiento → pagar saldo | F5: `registrarPagoSaldo`: `pagos`→PAGADO, saldo 0 + transacción SALDO ligada a la cita | G5: Crítica | H5: Real
A6: PS-H-05 | B6: 08 Payments Stripe | C6: Consultar pago | D6: Solicitud con pago | E6: 1. `consultarPago(solicitudId)` | F6: Devuelve el pago con saldo correcto | G6: Media | H6: Real
A7: PS-V-01 | B7: 08 Payments Stripe | C7: PaymentSheet cancelado | D7: Pago en curso | E7: 1. Cancelar el sheet | F7: `StripeException` → `null`; el flujo consumidor aborta sin registros | G7: Crítica | H7: Real
A8: PS-V-02 | B8: 08 Payments Stripe | C8: Intent fallido | D8: Edge function caída | E8: 1. Iniciar pago | F8: `crearIntent` falla → `PaymentsError`; sin PaymentSheet ni registros | G8: Alta | H8: Real
A9: PS-V-03 | B9: 08 Payments Stripe | C9: Saldo ya en cero | D9: Pago PAGADO | E9: 1. `registrarPagoSaldo` de nuevo | F9: Devuelve `false` (idempotencia); no crea segunda transacción | G9: Crítica | H9: Real
A10: PS-V-04 | B10: 08 Payments Stripe | C10: `consultarPago` inexistente | D10: Solicitud sin pago | E10: 1. Consultar | F10: Resultado vacío controlado; sin crash | G10: Media | H10: Real
A11: PS-V-05 | B11: 08 Payments Stripe | C11: Doble cobro de saldo | D11: Diálogo de finalización | E11: 1. Pagar saldo 2. Intentar finalizar de nuevo | F11: Segundo intento detecta saldo 0 y finaliza sin cobrar | G11: Crítica | H11: Real
A12: PS-G-01 | B12: 08 Payments Stripe | C12: Especialista no paga servicios | D12: Sesión de especialista | E12: 1. Intentar flujo de pago de servicio | F12: Las escrituras de solicitud/pago están ligadas a paciente; verificar RLS | G12: Alta | H12: Real
A13: PS-G-02 | B13: 08 Payments Stripe | C13: RLS de pagos | D13: Paciente A | E13: 1. Intentar leer `pagos` del paciente B | F13: RLS lo impide | G13: Alta | H13: Real
... A24: PS-S-03 | B24: 08 Payments Stripe | C24: PaymentsCubit como factory | D24: — | E24: 1. Dos pagos consecutivos | F24: Cada `sl<PaymentsCubit>()` crea instancia nueva; sin estado residual entre pagos | G24: Media | H24: Real

Sheet 09_treatment_execution
A1: ID | B1: Módulo | C1: Título | D1: Precondiciones | E1: Pasos | F1: Resultado esperado | G1: Prioridad | H1: Tipo | I1: Resultado | J1: Notas
A2: TE-H-01 | B2: 09 Treatment Execution | C2: Lista de citas | D2: Citas ejecutables | E2: 1. Entrar a `/specialist/mis-citas` | F2: Lista PROGRAMADA/EN_CAMINO/LLEGO/EN_PROCESO ordenada por `fecha_aceptacion`, con chip de estado, paciente, servicio, ciudad | G2: Crítica | H2: Real
A3: TE-H-02 | B3: 09 Treatment Execution | C3: Desplazamiento | D3: Cita PROGRAMADA | E3: 1. Abrir detalle 2. "Comenzar desplazamiento" | F3: Estado EN_CAMINO + registro en `historial_estados` | G3: Crítica | H3: Real
A4: TE-H-03 | B4: 09 Treatment Execution | C4: Llegada | D4: Cita EN_CAMINO | E4: 1. "Llegué al domicilio" | F4: Estado LLEGO | G4: Crítica | H4: Real
A5: TE-H-04 | B5: 09 Treatment Execution | C5: Inicio de servicio | D5: Cita LLEGO | E5: 1. "Iniciar servicio" | F5: Estado EN_PROCESO + `fecha_inicio`; `iniciarTratamiento` crea/recupera tratamiento INICIADO | G5: Crítica | H5: Real
A6: TE-H-05 | B6: 09 Treatment Execution | C6: Evaluación inicial | D6: Cita EN_PROCESO | E6: 1. Editar evaluación 2. Guardar | F6: `guardarEvaluacion` persiste | G6: Alta | H6: Real
A7: TE-H-06 | B7: 09 Treatment Execution | C7: Agregar insumo | D7: Cita EN_PROCESO | E7: 1. Diálogo: nombre, fabricante, lote, cantidad, unidad 2. Guardar | F7: `agregarProducto` crea fila (cantidad default 1) | G7: Alta | H7: Real
A8: TE-H-07 | B8: 09 Treatment Execution | C8: Eliminar insumo | D8: Insumo agregado | E8: 1. Eliminar | F8: `eliminarProducto` borra | G8: Media | H8: Real
A9: TE-H-08 | B9: 09 Treatment Execution | C9: Consentimiento firmado | D9: Cita EN_PROCESO | E9: 1. Sección firma → dibujar → confirmar | F9: PNG en bucket `firmas-consentimiento`; fila en `consentimientos_tratamiento` (tipo TRATAMIENTO_ESTETICO) | G9: Crítica | H9: Real
A10: TE-H-09 | B10: 09 Treatment Execution | C10: Finalización con saldo cobrado | D10: Cita con saldo pendiente | E10: 1. "Finalizar tratamiento" 2. Observaciones 3. "Cobrar y Finalizar" 4. Pagar | F10: Pago de saldo + `finalizar`: tratamiento COMPLETADO, cita FINALIZADA, `fecha_finalizacion`, historial tipo CITA; pop automático | G10: Crítica | H10: Real
A11: TE-H-10 | B11: 09 Treatment Execution | C11: Finalización sin saldo | D11: Cita pagada totalmente | E11: 1. "Finalizar tratamiento" 2. Confirmar | F11: Finaliza directo sin diálogo de cobro | G11: Alta | H11: Real
A12: TE-V-01 | B12: 09 Treatment Execution | C12: Insumo sin nombre | D12: Diálogo de producto | E12: 1. Nombre vacío 2. Guardar | F12: Validator bloquea | G12: Media | H12: Real
A13: TE-V-02 | B13: 09 Treatment Execution | C13: Firma vacía | D13: Pantalla de firma | E13: 1. Confirmar sin dibujar | F13: Validación impide guardar | G13: Media | H13: Real
... A34: TE-S-05 | B34: 09 Treatment Execution | C34: Estados sin Equatable | D34: — | E34: 1. Provocar rebuilds | F34: El cubit no usa Equatable: verificar rebuilds innecesarios o listeners duplicados | G34: Baja | H34: Real

Sheet 10_treatment_photos
A1: ID | B1: Módulo | C1: Título | D1: Precondiciones | E1: Pasos | F1: Resultado esperado | G1: Prioridad | H1: Tipo | I1: Resultado | J1: Notas
A2: TF-H-01 | B2: 10 Treatment Photos | C2: Carga de galería | D2: Tratamiento con fotos | E2: 1. Deep link con id válido | F2: Fotos ordenadas por `fecha_captura` desc; secciones PRE/POST/OTRO con contadores; grid 2 columnas con `CachedNetworkImage` | G2: Alta | H2: Real
A3: TF-H-02 | B3: 10 Treatment Photos | C3: Registrar por URL | D3: Formulario | E3: 1. URL válida + descripción + tipo 2. Guardar | F3: `registrarPorUrl` crea fila; aparece en la galería | G3: Alta | H3: Real
A4: TF-H-03 | B4: 10 Treatment Photos | C4: Subida binaria | D4: Imagen local | E4: 1. Subir imagen | F4: Bucket `fotografias-tratamiento`, path `<tratId>/<ts>_<ext>`; spinner `uploading`; fila con tipo | G4: Alta | H4: Real
A5: TF-H-04 | B5: 10 Treatment Photos | C5: Eliminar fotografía | D5: Foto existente | E5: 1. Eliminar 2. Confirmar | F5: `eliminarFotografia(id)` borra la fila; galería actualizada | G5: Media | H5: Real
A6: TF-V-01 | B6: 10 Treatment Photos | C6: URL vacía | D6: Formulario | E6: 1. Guardar sin URL | F6: Validator bloquea | G6: Media | H6: Real
A7: TF-V-02 | B7: 10 Treatment Photos | C7: URL inválida | D7: Formulario | E7: 1. URL malformada | F7: Error controlado al cargar la imagen; sin crash | G7: Media | H7: Real
A8: TF-V-03 | B8: 10 Treatment Photos | C8: Id de tratamiento inválido | D8: Deep link con id inexistente | E8: 1. Cargar | F8: Estado de error con Reintentar | G8: Alta | H8: Real
A9: TF-V-04 | B9: 10 Treatment Photos | C9: Galería vacía | D9: Tratamiento sin fotos | E9: 1. Cargar | F9: Vista vacía controlada | G9: Baja | H9: Real
A10: TF-G-01 | B10: 10 Treatment Photos | C10: Ruta autenticada | D10: Sin sesión | E10: 1. Deep link | F10: Guard `resolveAuthRedirect` envía a `/` (no es ruta pública) | G10: Alta | H10: Real
A11: TF-G-02 | B11: 10 Treatment Photos | C11: Fotos ajenas | D11: Paciente/especialista sin relación | E11: 1. Deep link con tratamiento ajeno | F11: RLS impide leer fotos de otro paciente | G11: Alta | H11: Real
A12: TF-G-03 | B12: 10 Treatment Photos | C12: Bucket público | D12: — | E12: 1. Inspeccionar políticas del bucket `fotografias-tratamiento` | F12: Escritura solo autenticados; lectura según diseño (URLs públicas) | G12: Media | H12: Real
A13: TF-E-01 | B13: 10 Treatment Photos | C13: Secuencia del cubit | D13: Carga | E13: 1. Observar estados | F13: `Loading` → `Loaded(fotografias, uploading)` | G13: Baja | H13: Real
... A21: TF-S-03 | B21: 10 Treatment Photos | C21: Doble columna de tipo | D21: Subida nueva | E21: 1. Subir foto 2. Inspeccionar fila en BD | F21: Escribe `tipo_fotografia` y además `tipo_foto` en minúsculas; verificar cuál es la columna oficial del esquema | G21: Media | H21: Real

Sheet 11_flujos_integrados
A1: FLUJOS INTEGRADOS E2E
A3: Nota: | B3: Los flujos E2E están documentados en docs/Pruebas manuales/11_flujos_integrados_e2e.md
A4: Formato: | B4: Son flujos paso a paso que cruzan múltiples módulos, no casos individuales
A5: Flujos: | B5: E2E-A: Paciente completo (registro → evaluación → reserva publicada)
B6: E2E-B: Especialista completo (registro → verificación → acepta cita)
B7: E2E-C: Marketplace y primera aceptación
B8: E2E-D: Ciclo de atención completo
B9: E2E-E: Financiero (depósito → saldo → liquidación → pago)
B10: E2E-F: Escenario integral (2 pacientes, 2 especialistas, concurrencia)
B11: E2E-G: Notificaciones y calificaciones

Sheet 12_solicitudes_reserva
A1: ID | B1: Módulo | C1: Título | D1: Precondiciones | E1: Pasos | F1: Resultado esperado | G1: Prioridad | H1: Tipo | I1: Resultado | J1: Notas
A2: RS-H-01 | B2: 12 Solicitudes Reserva | C2: Resumen de la solicitud | D2: Evaluación APTO | E2: 1. Entrar a `/services` 2. Tocar un servicio | F2: Navega a `SolicitudResumenScreen`: servicio, precio total, depósito (adelanto %), ubicación y radio | G2: Crítica | H2: Real | I2: ✅ | J2: E2E ítem 3
A3: RS-H-02 | B3: 12 Solicitudes Reserva | C3: Multi-servicio | D3: Resumen abierto | E3: 1. "Agregar" 2. Elegir otro servicio | F3: Se suma al resumen; total y depósito recalculan | G3: Alta | H3: Real | I3: ✅ | J3: E2E ítem 1
A4: RS-H-03 | B4: 12 Solicitudes Reserva | C4: Fecha/hora preferida | D4: Resumen abierto | E4: 1. "Elegir" 2. Seleccionar fecha y hora | F4: Muestra la preferencia en el resumen | G4: Media | H4: Real | I4: ✅ | J4: E2E ítem 3
A5: RS-H-04 | B5: 12 Solicitudes Reserva | C5: Crear + pagar depósito | D5: Dirección principal | E5: 1. "Pagar depósito" 2. PaymentSheet (4242) | F5: Solicitud `PENDIENTE_PAGO`; pago OK; confirmación → `PUBLICADA` (o pendiente webhook) | G5: Crítica | H5: Real | I5: ✅ | J5: E2E ítems 2, 4, 5
A6: RS-H-05 | B6: 12 Solicitudes Reserva | C6: Mis solicitudes | D6: Tras crear | E6: 1. Ir a `/mis-solicitudes` | F6: Lista con estado, servicios, montos y cita (si aceptada) | G6: Alta | H6: Real | I6: ✅ | J6: E2E ítem 2
A7: RS-H-06 | B7: 12 Solicitudes Reserva | C7: Pago totalidad | D7: Resumen abierto | E7: 1. Activar "¿Pagar totalidad?" 2. Pagar | F7: Depósito = total; `pagos.estado=PAGADO` | G7: Alta | H7: Real | I7: ⬜ | J7: Pendiente de prueba específica
A8: RS-V-01 | B8: 12 Solicitudes Reserva | C8: Sin dirección | D8: Paciente sin `direcciones_paciente` | E8: 1. Intentar pagar | F8: Bloqueado: "Registra tu dirección antes de confirmar" | G8: Crítica | H8: Real | I8: ⬜ | J8: Pendiente de prueba específica
A9: RS-V-02 | B9: 12 Solicitudes Reserva | C9: Sin evaluación APTO | D9: RN-020 no vigente | E9: 1. Tocar servicio del catálogo | F9: Modal de evaluación/requisitos (gate previo) | G9: Crítica | H9: Real | I9: ✅ | J9: Gate pre-existente verificado en catálogo (E2E 2026-08-20)
A10: RS-V-03 | B10: 12 Solicitudes Reserva | C10: Pago cancelado | D10: PaymentSheet | E10: 1. Cancelar el pago | F10: "El pago no se completó"; solicitud queda `PENDIENTE_PAGO` en Mis Solicitudes | G10: Alta | H10: Real | I10: ⬜ | J10: Pendiente de prueba específica
A11: RS-V-04 | B11: 12 Solicitudes Reserva | C11: Depósito mínimo | D11: Servicio de precio bajo | E11: 1. Pagar | F11: RPC valida ≥0.50 USD; error claro si aplica | G11: Media | H11: Real | I11: ⬜ | J11: Pendiente de prueba específica
A12: RS-V-05 | B12: 12 Solicitudes Reserva | C12: Publicación directa | D12: Manipular estado | E12: 1. UPDATE directo a `PUBLICADA` sin pago confirmado | F12: Trigger `trg_proteger_publicacion_solicitud` lo bloquea (42501/except) | G12: Crítica | H12: Real | I12: ✅ | J12: E2E ítem 5 (contra-prueba)
... A15: RS-G-03 | B15: 12 Solicitudes Reserva | C15: Especialista lee solicitud aceptada | D15: Cita asignada | E15: 1. Leer la solicitud ACEPTADA de su cita | F15: Visible (revela dirección exacta vía cita) | G15: Crítica | H15: Real | I15: ✅ | J15: E2E ítem 12

Sheet 13_admin_dashboard
A1: ID | B1: Módulo | C1: Título | D1: Precondiciones | E1: Pasos | F1: Resultado esperado | G1: Prioridad | H1: Tipo | I1: Resultado | J1: Notas
A2: AD-H-01 | B2: 13 Admin Dashboard | C2: Home con KPIs | E2: 1. Entrar a `/admin` | F2: KPIs cargados (RPC `admin_resumen_kpis`) | G2: Crítica | H2: Real
A3: AD-H-02 | B3: 13 Admin Dashboard | C3: Tarjetas Administrativo | E3: 1. Ver home | F3: Usuarios, Cuestionario, Catálogo, Licencias navegan | G3: Crítica | H3: Real
A4: AD-H-03 | B4: 13 Admin Dashboard | C4: Tarjetas Datos Maestros | E4: 1. Ver home | F4: Roles, Configuración, Comisiones, Especialidades, Médicos navegan | G4: Crítica | H4: Real
A5: AD-H-04 | B5: 13 Admin Dashboard | C5: Licencias propia | E5: 1. `/admin/licencias` | F5: Expedientes + aprobar/rechazar/bloquear + médicos | G5: Crítica | H5: Real
A6: AD-H-05 | B6: 13 Admin Dashboard | C6: Configuración editar | E6: 1. `/admin/configuracion` 2. Editar una clave | F6: Guarda y persiste | G6: Alta | H6: Real
A7: AD-H-06 | B7: 13 Admin Dashboard | C7: Roles CRUD | E7: 1. `/admin/datos-maestros/roles` 2. Nuevo rol + asignar permiso | F7: Se crea y asigna | G7: Alta | H7: Real
A8: AD-H-07 | B8: 13 Admin Dashboard | C8: Especialidades CRUD | E8: 1. `/admin/datos-maestros/especialidades` 2. Nueva + toggle | F8: Se crea y activa/desactiva | G8: Media | H8: Real
A9: AD-H-08 | B9: 13 Admin Dashboard | C9: Médicos regentes | E9: 1. `/admin/datos-maestros/medicos-regentes` 2. Registrar + aprobar | F9: Registra PENDIENTE; aprueba → ACTIVO | G9: Media | H9: Real
A10: AD-H-09 | B10: 13 Admin Dashboard | C10: Comisiones y liquidaciones | E10: 1. `/admin/datos-maestros/comisiones` | F10: Lista liquidaciones/pagos; enlace a configuración | G10: Media | H10: Real
A11: AD-V-01 | B11: 13 Admin Dashboard | C11: Guard por rol | E11: 1. Sesión especialista/paciente → `/admin/*` | F11: Redirige por rol | G11: Crítica | H11: Real
A12: AD-V-02 | B12: 13 Admin Dashboard | C12: RLS admin | E12: 1. Leer `configuracion_sistema`/`roles`/`comisiones` sin admin | F12: Sin filas (RLS) | G12: Crítica | H12: Real

Sheet 14_Notificaciones
A1: ID | B1: Módulo | C1: Título | D1: Precondiciones | E1: Pasos | F1: Resultado esperado | G1: Prioridad | H1: Tipo | I1: Resultado | J1: Notas
A2: NOT-01 | B2: Notificaciones | C2: Registro de dispositivo FCM | D2: Especialista logueado | E2: 1. Login especialista 2. Abrir app en browser con notificaciones habilitadas | F2: INSERT en dispositivos_usuario (usuario_id, token_fcm, plataforma WEB, activo=true) | G2: Alta | H2: Real
A3: NOT-02 | B3: Notificaciones | C3: Push solicitud nueva en zona | D3: Especialista APROBADO con geo | E3: 1. Paciente crea solicitud con dirección geo 2. Solicitud pasa a PUBLICADA | F3: Trigger trg_notificar_solicitud_publicada genera notif SOLICITUD_NUEVA a especialistas en radio | G3: Crítica | H3: Real
A4: NOT-03 | B4: Notificaciones | C4: Push solicitud aceptada | D4: Solicitud PUBLICADA | E4: 1. Especialista acepta solicitud | F4: Notif SOLICITUD_ACEPTADA al paciente + cita PROGRAMADA creada | G4: Crítica | H4: Real
A5: NOT-04 | B5: Notificaciones | C5: Push cambio estado cita | D5: Cita PROGRAMADA | E5: 1. Especialista cambia a EN_CAMINO 2. Luego a LLEGO | F5: 2 notifs CITA_ESTADO al paciente (trigger trg_notificar_cambio_estado_cita) | G5: Alta | H5: Real
A6: NOT-05 | B6: Notificaciones | C6: Recordatorio previo a cita | D6: Cita PROGRAMADA con fecha_inicio en 2h | E6: 1. Esperar a que pg_cron ejecute enviar_recordatorios_cita (cada 15min) | F6: Notif RECORDATORIO_CITA al paciente + fila en recordatorios_cita | G6: Alta | H6: Real
A7: NOT-06 | B7: Notificaciones | C7: Push documento rechazado | D7: Especialista con documentos | E7: 1. Admin rechaza documento | F7: Notif DOCUMENTO_RECHAZADO al especialista | G7: Media | H7: Real
A8: NOT-07 | B8: Notificaciones | C8: Push verificación aprobada | D8: Especialista EN_REVISION | E8: 1. Admin aprueba verificación | F8: Notif VERIFICACION_APROBADA al especialista | G8: Media | H8: Real
A9: NOT-08 | B9: Notificaciones | C9: Notificación in-app visible | D9: Notificaciones generadas | E9: 1. Usuario abre app 2. Revisa campana de notificaciones | F9: Lista de notificaciones in-app visible con tipo, mensaje, fecha | G9: Alta | H9: Real
A10: NOT-09 | B10: Notificaciones | C10: Push FCM en dispositivo físico | D10: Dispositivo real + Firebase config | E10: 1. Instalar PWA en móvil 2. Generar notificación | F10: Push recibido en sistema operativo (MANUAL - requiere dispositivo) | G10: Alta | H10: Real
A11: NOT-10 | B11: Notificaciones | C11: Sin notificaciones sin token FCM | D11: Usuario sin dispositivos_usuario | E11: 1. Generar evento que notifica | F11: Solo notif in-app, sin push FCM | G11: Media | H11: Simulado
A12: NOT-11 | B12: Notificaciones | C12: Idempotencia recordatorio | D12: Cita con recordatorio ya enviado | E12: 1. Ejecutar enviar_recordatorios_cita de nuevo | F12: No duplica recordatorio (UNIQUE en recordatorios_cita.cita_id) | G12: Media | H12: Simulado
A13: NOT-12 | B13: Notificaciones | C13: Notificación a usuario inexistente | D13: usuario_id inválido | E13: 1. Llamar notificar_usuario_push con UUID inexistente | F13: Función maneja gracefully (no crash) | G13: Baja | H13: Simulado
... A16: NOT-15 | B16: Notificaciones | C16: Notificación tras logout | D16: Usuario deslogueado | E16: 1. Logout 2. Generar evento | F16: No recibe push (token desactivado por FcmTokenService.deactivateCurrentDevice) | G16: Alta | H16: Simulado

Sheet 15_Calificaciones
A1: ID | B1: Módulo | C1: Título | D1: Precondiciones | E1: Pasos | F1: Resultado esperado | G1: Prioridad | H1: Tipo | I1: Resultado | J1: Notas
A2: CAL-01 | B2: Calificaciones | C2: Paciente califica especialista | D2: Cita FINALIZADA | E2: 1. Paciente abre mis solicitudes 2. Cita finalizada 3. Click "Calificar especialista" 4. 5 estrellas + comentario 5. Enviar | F2: RPC registrar_evaluacion retorna {ok:true, evaluacion_id}. Fila en evaluaciones_servicio con evaluador_id=paciente, evaluado_especialista_id | G2: Crítica | H2: Real
A3: CAL-02 | B3: Calificaciones | C3: Especialista califica paciente | D3: Cita FINALIZADA | E3: 1. Especialista abre detalle cita 2. Click "Calificar paciente" 3. 4 estrellas + comentario 4. Enviar | F3: RPC registrar_evaluacion retorna {ok:true}. Fila con evaluador_id=especialista, evaluado_paciente_id | G3: Crítica | H3: Real
A4: CAL-03 | B4: Calificaciones | C4: No calificar antes de finalizar | D4: Cita PROGRAMADA | E4: 1. Intentar registrar_evaluacion | F4: {ok:false, motivo:CITA_NO_FINALIZADA} | G4: Alta | H4: Simulado
A5: CAL-04 | B5: Calificaciones | C5: No segunda calificación | D5: Ya evaluado | E5: 1. Mismo evaluador intenta calificar de nuevo | F5: {ok:false, motivo:YA_EVALUADO} | G5: Alta | H5: Simulado
A6: CAL-05 | B6: Calificaciones | C6: Puntuación inválida | D6: Cita FINALIZADA | E6: 1. registrar_evaluacion con puntuacion=6 | F6: {ok:false, motivo:PUNTUACION_INVALIDA} | G6: Media | H6: Simulado
A7: CAL-06 | B7: Calificaciones | C7: No participante califica | D7: Admin u otro usuario | E7: 1. Admin intenta calificar cita donde no participó | F7: {ok:false, motivo:NO_AUTORIZADO} | G7: Alta | H7: Simulado
A8: CAL-07 | B8: Calificaciones | C8: Promedio especialista | D8: Especialista con 2 evaluaciones (5,4) | E8: 1. get_promedio_especialista | F8: {promedio:4.5, total:2} | G8: Alta | H8: Real
A9: CAL-08 | B9: Calificaciones | C9: Promedio en marketplace | D9: Especialista con evaluaciones | E9: 1. Abrir mapa 2. Click especialista 3. Ver detalle sheet | F9: Promedio y total visibles en _EspecialistaDetailSheet | G9: Media | H9: Real
A10: CAL-09 | B10: Calificaciones | C10: Promedio en perfil especialista | D10: Especialista logueado con evaluaciones | E10: 1. Abrir perfil 2. Ver sección calificación | F10: _calificacionRow muestra promedio | G10: Media | H10: Real
A11: CAL-10 | B11: Calificaciones | C11: UNIQUE cita_id+evaluador_id | D11: BD con evaluaciones | E11: 1. Verificar constraint en BD | F11: UNIQUE (cita_id, evaluador_id) presente | G11: Alta | H11: Simulado
A12: CAL-11 | B12: Calificaciones | C12: CHECK puntuación 1-5 | D12: BD | E12: 1. Verificar constraint | F12: CHECK (puntuacion BETWEEN 1 AND 5) | G12: Media | H12: Simulado
A13: CAL-12 | B13: Calificaciones | C13: Comentario largo | D13: Cita FINALIZADA | E13: 1. Calificar con comentario de 500 caracteres | F13: Se guarda completo (text sin límite) | G13: Baja | H13: Simulado
A14: CAL-13 | B14: Calificaciones | C14: Sin comentario | D14: Cita FINALIZADA | E14: 1. Calificar solo con estrellas | F14: evaluaciones_servicio.comentario = NULL (permitido) | G14: Baja | H14: Simulado

Sheet 16_Liquidaciones
A1: ID | B1: Módulo | C1: Título | D1: Precondiciones | E1: Pasos | F1: Resultado esperado | G1: Prioridad | H1: Tipo | I1: Resultado | J1: Notas
A2: LIQ-01 | B2: Liquidaciones | C2: Generar liquidaciones | D2: Citas FINALIZADAS pagadas del período | E2: 1. Admin abre conciliación 2. Selecciona período 3. Click "Generar liquidación" | F2: RPC generar_liquidaciones agrupa por especialista. INSERT liquidaciones_especialistas (estado PENDIENTE) + liquidacion_detalles + comisiones | G2: Crítica | H2: Real
A3: LIQ-02 | B3: Liquidaciones | C3: Idempotencia liquidación | D3: Cita ya liquidada | E3: 1. Generar liquidaciones de nuevo | F3: Cita ya liquidada NO se incluye (NOT EXISTS liquidacion_detalles) | G3: Crítica | H3: Simulado
A4: LIQ-03 | B4: Liquidaciones | C4: Máquina estados liquidación | D4: Liquidación PENDIENTE | E4: 1. Cambiar a EN_REVISION 2. Luego a APROBADA 3. Luego a PAGADA | F4: Trigger trg_validar_transicion_estado_liquidacion permite transiciones válidas | G4: Crítica | H4: Real
A5: LIQ-04 | B5: Liquidaciones | C5: Transición inválida | D5: Liquidación PENDIENTE | E5: 1. Intentar cambiar directo a PAGADA | F5: Trigger rechaza (transición no permitida) | G5: Alta | H5: Simulado
A6: LIQ-05 | B6: Liquidaciones | C6: Registrar pago externo | D6: Liquidación APROBADA | E6: 1. Admin abre diálogo "Registrar pago" 2. Método: Transferencia 3. Referencia, monto, notas 4. Adjuntar comprobante (image_picker) 5. Enviar | F6: RPC registrar_pago_especialista INSERT pagos_especialistas + UPDATE liquidación PAGADA + fecha_pago. Comprobante subido a bucket comprobantes-pagos | G6: Crítica | H6: Real
A7: LIQ-06 | B7: Liquidaciones | C7: Pago monto incorrecto | D7: Liquidación APROBADA monto_pagar=144 | E7: 1. Registrar pago con monto=100 | F7: Permite (monto por defecto = monto_pagar, pero se puede especificar otro) | G7: Media | H7: Simulado
A8: LIQ-07 | B8: Liquidaciones | C8: Comprobante URL firmada | D8: Pago con comprobante | E8: 1. Admin o especialista ve comprobante | F8: firmarComprobante genera URL firmada válida (bucket privado) | G8: Alta | H8: Real
A9: LIQ-08 | B9: Liquidaciones | C9: Solo admin registra pago | D9: Especialista logueado | E9: 1. Intentar registrar_pago_especialista | F9: RLS/rechaza (solo admin) | G9: Alta | H9: Simulado
A10: LIQ-09 | B10: Liquidaciones | C10: Liquidación ya pagada | D10: Liquidación PAGADA | E10: 1. Intentar registrar pago de nuevo | F10: {ok:false, motivo:YA_PAGADA} | G10: Alta | H10: Simulado
A11: LIQ-10 | B11: Liquidaciones | C11: Período por defecto | D11: Admin abre conciliación | E11: 1. Ver selector de período | F11: Por defecto: última semana completa (lunes-domingo) según inicio_semana_liquidacion config | G11: Media | H11: Real
A12: LIQ-11 | B12: Liquidaciones | C12: Comisión calculada | D12: Liquidación generada | E12: 1. Ver liquidacion_detalles | F12: comision_aplicada = monto_servicio * comision_porcentaje / 100. monto_especialista = monto_servicio - comision | G12: Alta | H12: Real
A13: LIQ-12 | B13: Liquidaciones | C13: Anular liquidación | D13: Liquidación PENDIENTE | E13: 1. Cambiar estado a ANULADA | F13: Transición permitida. Liquidación no se procesa más | G13: Media | H13: Real
... A19: LIQ-18 | B19: Liquidaciones | C19: Comprobante grande | D19: Imagen >5MB | E19: 1. Subir comprobante grande | F19: Storage acepta (sin límite explícito en bucket) | G19: Baja | H19: Simulado

Sheet 17_Historial_Liq
A1: ID | B1: Módulo | C1: Título | D1: Precondiciones | E1: Pasos | F1: Resultado esperado | G1: Prioridad | H1: Tipo | I1: Resultado | J1: Notas
A2: HLIQ-01 | B2: Historial Liq | C2: Especialista ve sus liquidaciones | D2: Especialista con liquidaciones | E2: 1. Login especialista 2. Home → "Mis liquidaciones" | F2: Lista de liquidaciones del especialista (RLS specialist_select) | G2: Crítica | H2: Real
A3: HLIQ-02 | B3: Historial Liq | C3: Liquidación estado visible | D3: Liquidación en distintos estados | E3: 1. Ver lista | F3: Chip de estado coloreado (PENDIENTE/EN_REVISION/APROBADA/PAGADA/ANULADA) | G3: Alta | H3: Real
A4: HLIQ-03 | B4: Historial Liq | C4: Ver comprobante pago | D4: Liquidación PAGADA con comprobante | E4: 1. Click "Ver comprobante" | F4: URL firmada abre imagen en nueva pestaña | G4: Alta | H4: Real
A5: HLIQ-04 | B5: Historial Liq | C5: Monto neto visible | D5: Liquidación | E5: 1. Ver tarjeta | F5: monto_pagar visible | G5: Media | H5: Real
A6: HLIQ-05 | B6: Historial Liq | C6: Período visible | D6: Liquidación | E6: 1. Ver tarjeta | F6: fecha_inicio y fecha_fin visibles | G6: Media | H6: Real
A7: HLIQ-06 | B7: Historial Liq | C7: Método pago visible | D7: Liquidación PAGADA | E7: 1. Ver pago asociado | F7: metodo_pago visible | G7: Media | H7: Real
A8: HLIQ-07 | B8: Historial Liq | C8: Solo lectura | D8: Especialista | E8: 1. Intentar cambiar estado o registrar pago | F8: No hay botones/API. Solo SELECT (RLS) | G8: Alta | H8: Simulado
A9: HLIQ-08 | B9: Historial Liq | C9: Sin liquidaciones | D9: Especialista nuevo sin liquidaciones | E9: 1. Abrir Mis liquidaciones | F9: Lista vacía, mensaje "No hay liquidaciones" | G9: Baja | H9: Simulado

Sheet 18_Conciliacion
A1: ID | B1: Módulo | C1: Título | D1: Precondiciones | E1: Pasos | F1: Resultado esperado | G1: Prioridad | H1: Tipo | I1: Resultado | J1: Notas
A2: CON-01 | B2: Conciliacion | C2: Tab Transacciones | D2: Admin logueado | E2: 1. Abrir conciliación 2. Tab "Transacciones" | F2: Lista de transacciones (DEPOSITO, SALDO, etc.) con filtros | G2: Alta | H2: Real
A3: CON-02 | B3: Conciliacion | C3: Tab Detalle por cita | D3: Admin logueado | E3: 1. Tab "Detalle por cita" 2. Seleccionar período 3. Seleccionar cita de lista 4. Consultar | F3: Detalle financiero: monto_total, deposito, saldo_pendiente, estado_pago, comisión | G3: Alta | H3: Real
A4: CON-03 | B4: Conciliacion | C4: Tab Citas terminadas | D4: Admin logueado | E4: 1. Tab "Citas terminadas" 2. Seleccionar período | F4: Lista de citas FINALIZADA del período (incluye liquidadas y pendientes de pago) | G4: Crítica | H4: Real
A5: CON-04 | B5: Conciliacion | C5: Cita liquidada marcada | D5: Cita ya liquidada en período | E5: 1. Ver lista citas terminadas | F5: Cita aparece con chip azul "LIQUIDADA" | G5: Alta | H5: Real
A6: CON-05 | B6: Conciliacion | C6: Cita con saldo pendiente | D6: Cita FINALIZADA con saldo>0 | E6: 1. Ver lista citas terminadas | F6: Cita aparece con chip ámbar "TERMINADA" + texto "Aún con saldo pendiente: no es elegible" | G6: Alta | H6: Real
A7: CON-06 | B7: Conciliacion | C7: Generar liquidación | D7: Citas elegibles (no liquidadas) | E7: 1. Click "Generar liquidación" | F7: RPC generar_liquidaciones ejecutado. Mensaje "Liquidación generada: N especialista(s), N cita(s), $X a pagar" | G7: Crítica | H7: Real
A8: CON-07 | B8: Conciliacion | C8: Seleccionar período personalizado | D8: Admin en Citas terminadas | E8: 1. Click "Seleccionar período" 2. Elegir rango de fechas 3. Confirmar | F8: Lista se recarga con citas del nuevo período | G8: Media | H8: Real
A9: CON-08 | B9: Conciliacion | C9: Período por defecto | D9: Admin abre conciliación | E9: 1. Ver selector de período | F9: Última semana completa (lunes-domingo) | G9: Media | H9: Real
A10: CON-09 | B10: Conciliacion | C10: Consulta directa por UUID | D10: Admin en Detalle por cita | E10: 1. Pegar UUID de cita en campo 2. Consultar | F10: Detalle financiero de esa cita específica | G10: Media | H10: Real
A11: CON-10 | B11: Conciliacion | C11: Sin citas en período | D11: Período sin citas FINALIZADAS | E11: 1. Seleccionar período vacío | F11: Mensaje "No hay citas terminadas en el período" | G11: Baja | H11: Simulado
A12: CON-11 | B12: Conciliacion | C12: Transacciones filtros | D12: Tab Transacciones | E12: 1. Aplicar filtros (estado, tipo, fecha) | F12: Lista filtrada correctamente | G12: Media | H12: Real
A13: CON-12 | B13: Conciliacion | C13: Detalle financiero montos | D13: Cita con pago | E13: 1. Ver detalle | F13: monto_total, deposito, saldo_pendiente correctos (no en cero) | G13: Crítica | H13: Real

Sheet 19_Sesion_Web
A1: ID | B1: Módulo | C1: Título | D1: Precondiciones | E1: Pasos | F1: Resultado esperado | G1: Prioridad | H1: Tipo | I1: Resultado | J1: Notas
A2: SW-01 | B2: Sesion Web | C2: Cerrar pestaña limpia sesión | D2: Usuario logueado en web | E2: 1. Cerrar pestaña del navegador 2. Reabrir app | F2: Pantalla de login (sesión borrada por pagehide listener) | G2: Crítica | H2: Real
A3: SW-02 | B3: Sesion Web | C3: F5 limpia sesión | D3: Usuario logueado en web | E3: 1. Presionar F5 (refresh) 2. Esperar recarga | F3: Pantalla de login (sesión borrada por pagehide) | G3: Crítica | H3: Real
A4: SW-03 | B4: Sesion Web | C4: Navegación SPA no limpia | D4: Usuario logueado | E4: 1. Navegar entre rutas (GoRouter) 2. Cambiar de pantalla | F4: Sesión se mantiene (no dispara pagehide) | G4: Alta | H4: Real
A5: SW-04 | B5: Sesion Web | C5: PKCE verifier preservado | D5: Link de confirmación pendiente | E5: 1. Cerrar pestaña 2. Abrir link de confirmación | F5: Confirmación funciona (verifier PKCE en claves flutter. no se borra) | G5: Alta | H5: Real
A6: SW-05 | B6: Sesion Web | C6: Mobile no limpia en detached | D6: App móvil | E6: 1. Cerrar app 2. Reabrir | F6: Sesión se mantiene (clearLocalSession en detached, pero gotrue ya limpió) | G6: Media | H6: Real
A7: SW-06 | B7: Sesion Web | C7: LocalStorage limpiado | D7: Sesión activa | E7: 1. Abrir DevTools 2. Application → Local Storage 3. Cerrar pestaña 4. Reabrir DevTools | F7: Clave sb-hhyjremkguvphmjuaazp-auth-token eliminada | G7: Alta | H7: Simulado
